<?xml version="1.0" encoding="UTF-8"?>

<!-- generated on 2023-03-18 16:50:59 by Eclipse SUMO netedit Version 1.15.0
<configuration xmlns:xsi="http://www.w3.org/2001/XMLSchema-instance" xsi:noNamespaceSchemaLocation="http://sumo.dlr.de/xsd/netconvertConfiguration.xsd">

    <input>
        <sumo-net-file value="C:\Users\Paulinho\Desktop\Master-Thesis\sumo\vci.net.xml.gz"/>
    </input>

    <output>
        <output-file value="C:\Users\Paulinho\Desktop\Master-Thesis\nodes\no_barrosa.net.xml"/>
        <output.street-names value="true"/>
    </output>

    <processing>
        <geometry.min-radius.fix.railways value="false"/>
        <geometry.max-grade.fix value="false"/>
        <offset.disable-normalization value="true"/>
        <lefthand value="0"/>
    </processing>

    <junctions>
        <no-turnarounds value="true"/>
        <junctions.corner-detail value="5"/>
        <junctions.limit-turn-speed value="5.50"/>
        <rectangular-lane-cut value="0"/>
    </junctions>

    <pedestrian>
        <walkingareas value="0"/>
    </pedestrian>

    <netedit>
        <additional-files value="C:\Users\Paulinho\Desktop\Master-Thesis\nodes\no_barrosa_poi.xml"/>
    </netedit>

</configuration>
-->

<net version="1.9" junctionCornerDetail="5" limitTurnSpeed="5.50" xmlns:xsi="http://www.w3.org/2001/XMLSchema-instance" xsi:noNamespaceSchemaLocation="http://sumo.dlr.de/xsd/net_file.xsd">

    <location netOffset="-524914.43,-4544541.91" convBoundary="6618.21,7547.04,7435.35,8100.91" origBoundary="-8.702913,41.051318,-8.236192,41.279522" projParameter="+proj=utm +zone=29 +ellps=WGS84 +datum=WGS84 +units=m +no_defs"/>

    <type id="highway.bridleway" priority="1" numLanes="1" speed="2.78" allow="pedestrian" oneway="1" width="2.00"/>
    <type id="highway.bus_guideway" priority="1" numLanes="1" speed="27.78" allow="bus" oneway="1"/>
    <type id="highway.cycleway" priority="1" numLanes="1" speed="5.56" allow="bicycle" oneway="0" width="1.00"/>
    <type id="highway.footway" priority="1" numLanes="1" speed="2.78" allow="pedestrian" oneway="1" width="2.00"/>
    <type id="highway.ford" priority="1" numLanes="1" speed="2.78" allow="army" oneway="0"/>
    <type id="highway.living_street" priority="2" numLanes="1" speed="2.78" disallow="tram rail_urban rail rail_electric rail_fast ship" oneway="0"/>
    <type id="highway.motorway" priority="14" numLanes="2" speed="39.44" allow="private emergency authority army vip passenger hov taxi bus coach delivery truck trailer motorcycle evehicle custom1 custom2" oneway="1"/>
    <type id="highway.motorway_link" priority="9" numLanes="1" speed="22.22" allow="private emergency authority army vip passenger hov taxi bus coach delivery truck trailer motorcycle evehicle custom1 custom2" oneway="1"/>
    <type id="highway.path" priority="1" numLanes="1" speed="5.56" allow="pedestrian bicycle" oneway="0" width="2.00"/>
    <type id="highway.pedestrian" priority="1" numLanes="1" speed="2.78" allow="pedestrian" oneway="1" width="2.00"/>
    <type id="highway.primary" priority="12" numLanes="2" speed="27.78" disallow="tram rail_urban rail rail_electric rail_fast ship" oneway="0"/>
    <type id="highway.primary_link" priority="7" numLanes="1" speed="22.22" disallow="tram rail_urban rail rail_electric rail_fast ship" oneway="0"/>
    <type id="highway.raceway" priority="15" numLanes="2" speed="83.33" allow="vip" oneway="0"/>
    <type id="highway.residential" priority="3" numLanes="1" speed="13.89" disallow="tram rail_urban rail rail_electric rail_fast ship" oneway="0"/>
    <type id="highway.secondary" priority="11" numLanes="1" speed="27.78" disallow="tram rail_urban rail rail_electric rail_fast ship" oneway="0"/>
    <type id="highway.secondary_link" priority="6" numLanes="1" speed="22.22" disallow="tram rail_urban rail rail_electric rail_fast ship" oneway="0"/>
    <type id="highway.service" priority="1" numLanes="1" speed="5.56" allow="pedestrian delivery bicycle" oneway="0"/>
    <type id="highway.stairs" priority="1" numLanes="1" speed="1.39" allow="pedestrian" oneway="1" width="2.00"/>
    <type id="highway.step" priority="1" numLanes="1" speed="1.39" allow="pedestrian" oneway="1" width="2.00"/>
    <type id="highway.steps" priority="1" numLanes="1" speed="1.39" allow="pedestrian" oneway="1" width="2.00"/>
    <type id="highway.tertiary" priority="10" numLanes="1" speed="22.22" disallow="tram rail_urban rail rail_electric rail_fast ship" oneway="0"/>
    <type id="highway.tertiary_link" priority="5" numLanes="1" speed="22.22" disallow="tram rail_urban rail rail_electric rail_fast ship" oneway="0"/>
    <type id="highway.track" priority="1" numLanes="1" speed="5.56" allow="pedestrian motorcycle moped bicycle" oneway="0"/>
    <type id="highway.trunk" priority="13" numLanes="2" speed="27.78" disallow="pedestrian bicycle tram rail_urban rail rail_electric rail_fast ship" oneway="0"/>
    <type id="highway.trunk_link" priority="8" numLanes="1" speed="22.22" disallow="pedestrian bicycle tram rail_urban rail rail_electric rail_fast ship" oneway="0"/>
    <type id="highway.unclassified" priority="4" numLanes="1" speed="13.89" disallow="tram rail_urban rail rail_electric rail_fast ship" oneway="0"/>
    <type id="highway.unsurfaced" priority="1" numLanes="1" speed="8.33" disallow="tram rail_urban rail rail_electric rail_fast ship" oneway="0"/>
    <type id="railway.highspeed" priority="21" numLanes="1" speed="69.44" allow="rail_fast" oneway="1"/>
    <type id="railway.light_rail" priority="19" numLanes="1" speed="27.78" allow="rail_urban" oneway="1"/>
    <type id="railway.preserved" priority="16" numLanes="1" speed="27.78" allow="rail" oneway="1"/>
    <type id="railway.rail" priority="20" numLanes="1" speed="44.44" allow="rail" oneway="1"/>
    <type id="railway.subway" priority="18" numLanes="1" speed="27.78" allow="rail_urban" oneway="1"/>
    <type id="railway.tram" priority="17" numLanes="1" speed="13.89" allow="tram" oneway="1"/>

    <edge id=":1110673494_0" function="internal">
        <lane id=":1110673494_0_0" index="0" allow="private emergency authority army vip passenger hov taxi bus coach delivery truck trailer motorcycle evehicle custom1 custom2" speed="22.22" length="3.71" shape="7264.38,7898.64 7263.29,7898.49 7262.56,7898.32 7261.84,7898.08 7260.80,7897.73"/>
    </edge>
    <edge id=":1110673494_1" function="internal">
        <lane id=":1110673494_1_0" index="0" allow="private emergency authority army vip passenger hov taxi bus coach delivery truck trailer motorcycle evehicle custom1 custom2" speed="22.22" length="3.08" shape="7264.73,7895.46 7261.67,7895.07"/>
    </edge>
    <edge id=":1110673581_0" function="internal">
        <lane id=":1110673581_0_0" index="0" allow="private emergency authority army vip passenger hov taxi bus coach delivery truck trailer motorcycle evehicle custom1 custom2" speed="14.92" length="13.50" shape="7217.44,7892.72 7214.75,7891.08 7212.00,7890.60 7208.72,7890.60 7204.45,7890.37"/>
    </edge>
    <edge id=":1110673581_1" function="internal">
        <lane id=":1110673581_1_0" index="0" allow="private emergency authority army vip passenger hov taxi bus coach delivery truck trailer motorcycle evehicle custom1 custom2" speed="22.22" length="13.82" shape="7218.51,7889.09 7204.83,7887.19"/>
    </edge>
    <edge id=":1110673649_0" function="internal">
        <lane id=":1110673649_0_0" index="0" allow="private emergency authority army vip passenger hov taxi bus coach delivery truck trailer motorcycle evehicle custom1 custom2" speed="25.00" length="2.73" shape="6896.89,7975.53 6895.94,7978.09"/>
    </edge>
    <edge id=":1110673649_1" function="internal">
        <lane id=":1110673649_1_0" index="0" disallow="tram rail_urban rail rail_electric rail_fast ship" speed="27.78" length="2.94" shape="6893.87,7974.37 6892.90,7977.07"/>
        <lane id=":1110673649_1_1" index="1" disallow="tram rail_urban rail rail_electric rail_fast ship" speed="27.78" length="2.94" shape="6890.89,7973.22 6889.87,7976.05"/>
    </edge>
    <edge id=":1110673725_0" function="internal">
        <lane id=":1110673725_0_0" index="0" allow="private emergency authority army vip passenger hov taxi bus coach delivery truck trailer motorcycle evehicle custom1 custom2" speed="22.22" length="3.35" shape="7157.98,7884.94 7154.65,7884.52"/>
    </edge>
    <edge id=":1110673725_1" function="internal">
        <lane id=":1110673725_1_0" index="0" allow="private emergency authority army vip passenger hov taxi bus coach delivery truck trailer motorcycle evehicle custom1 custom2" speed="22.22" length="3.31" shape="7158.35,7881.76 7157.37,7881.64 7156.71,7881.53 7156.06,7881.35 7155.12,7881.05"/>
    </edge>
    <edge id=":269354454_0" function="internal">
        <lane id=":269354454_0_0" index="0" allow="private emergency authority army vip passenger hov taxi bus coach delivery truck trailer motorcycle evehicle custom1 custom2" speed="23.61" length="3.29" shape="6742.83,7691.35 6743.48,7692.08 6743.95,7692.56 6744.46,7693.00 6745.23,7693.60"/>
    </edge>
    <edge id=":269354454_1" function="internal">
        <lane id=":269354454_1_0" index="0" allow="private emergency authority army vip passenger hov taxi bus coach delivery truck trailer motorcycle evehicle custom1 custom2" speed="25.00" length="3.36" shape="6740.43,7693.48 6742.66,7695.95"/>
        <lane id=":269354454_1_1" index="1" allow="private emergency authority army vip passenger hov taxi bus coach delivery truck trailer motorcycle evehicle custom1 custom2" speed="25.00" length="3.36" shape="6738.04,7695.60 6740.30,7698.11"/>
    </edge>
    <edge id=":269354459_0" function="internal">
        <lane id=":269354459_0_0" index="0" allow="private emergency authority army vip passenger hov taxi bus coach delivery truck trailer motorcycle evehicle custom1 custom2" speed="25.00" length="7.98" shape="7040.13,7845.19 7042.41,7845.46 7044.01,7845.24 7045.62,7844.97 7047.93,7845.08"/>
        <lane id=":269354459_0_1" index="1" allow="private emergency authority army vip passenger hov taxi bus coach delivery truck trailer motorcycle evehicle custom1 custom2" speed="25.00" length="7.98" shape="7039.40,7848.30 7041.75,7848.59 7043.40,7848.39 7045.06,7848.12 7047.44,7848.24"/>
    </edge>
    <edge id=":331868361#0-AddedOffRampNode_0" function="internal">
        <lane id=":331868361#0-AddedOffRampNode_0_0" index="0" allow="private emergency authority army vip passenger hov taxi bus coach delivery truck trailer motorcycle evehicle custom1 custom2" speed="22.22" length="9.25" shape="6810.93,7723.45 6813.63,7722.76 6815.11,7720.81 6816.62,7718.69 6819.43,7717.48"/>
        <lane id=":331868361#0-AddedOffRampNode_0_1" index="1" allow="private emergency authority army vip passenger hov taxi bus coach delivery truck trailer motorcycle evehicle custom1 custom2" speed="22.22" length="9.25" shape="6810.93,7723.45 6813.43,7723.24 6815.05,7722.38 6816.67,7721.38 6819.17,7720.72"/>
        <lane id=":331868361#0-AddedOffRampNode_0_2" index="2" allow="private emergency authority army vip passenger hov taxi bus coach delivery truck trailer motorcycle evehicle custom1 custom2" speed="22.22" length="9.25" shape="6810.93,7723.45 6813.30,7723.73 6814.92,7723.98 6816.54,7724.10 6818.90,7723.97"/>
    </edge>
    <edge id=":3389563082_0" function="internal">
        <lane id=":3389563082_0_0" index="0" disallow="tram rail_urban rail rail_electric rail_fast ship" speed="12.96" length="11.53" shape="6978.99,7707.12 6982.12,7705.85 6984.13,7704.59 6985.72,7702.81 6987.59,7699.98"/>
        <lane id=":3389563082_0_1" index="1" disallow="tram rail_urban rail rail_electric rail_fast ship" speed="13.39" length="12.31" shape="6978.99,7707.12 6982.58,7706.22 6985.30,7705.86 6987.58,7704.94 6989.84,7702.39"/>
    </edge>
    <edge id=":3389563082_2" function="internal">
        <lane id=":3389563082_2_0" index="0" disallow="tram rail_urban rail rail_electric rail_fast ship" speed="13.17" length="12.22" shape="6978.99,7707.12 6982.54,7705.80 6985.14,7705.14 6987.75,7705.25 6991.33,7706.25"/>
        <lane id=":3389563082_2_1" index="1" disallow="tram rail_urban rail rail_electric rail_fast ship" speed="12.58" length="12.22" shape="6980.10,7710.12 6983.33,7708.97 6985.70,7708.47 6988.08,7708.68 6991.34,7709.63"/>
    </edge>
    <edge id=":3389563087_0" function="internal">
        <lane id=":3389563087_0_0" index="0" disallow="tram rail_urban rail rail_electric rail_fast ship" speed="27.78" length="15.32" shape="6995.55,7762.01 6991.41,7763.86 6988.69,7765.37 6986.06,7767.05 6982.17,7769.41"/>
        <lane id=":3389563087_0_1" index="1" disallow="tram rail_urban rail rail_electric rail_fast ship" speed="27.78" length="15.76" shape="6995.55,7762.01 6991.11,7763.44 6987.89,7763.98 6984.76,7764.68 6980.57,7766.63"/>
    </edge>
    <edge id=":3389563087_2" function="internal">
        <lane id=":3389563087_2_0" index="0" disallow="tram rail_urban rail rail_electric rail_fast ship" speed="17.13" length="16.05" shape="6995.55,7762.01 6991.01,7763.60 6987.68,7763.99 6984.26,7763.54 6979.45,7762.56"/>
        <lane id=":3389563087_2_1" index="1" disallow="tram rail_urban rail rail_electric rail_fast ship" speed="16.64" length="16.05" shape="6994.34,7759.05 6990.05,7760.50 6986.91,7760.76 6983.68,7760.22 6979.15,7759.25"/>
    </edge>
    <edge id=":3389563088_0" function="internal">
        <lane id=":3389563088_0_0" index="0" disallow="tram rail_urban rail rail_electric rail_fast ship" speed="12.54" length="1.02" shape="7007.51,7714.90 7007.86,7715.18 7008.09,7715.39 7008.28,7715.63 7008.53,7716.01"/>
        <lane id=":3389563088_0_1" index="1" disallow="tram rail_urban rail rail_electric rail_fast ship" speed="27.78" length="1.02" shape="7005.53,7717.41 7005.65,7717.51 7005.72,7717.58 7005.79,7717.66 7005.87,7717.78"/>
    </edge>
    <edge id=":3389563089_0" function="internal">
        <lane id=":3389563089_0_0" index="0" disallow="tram rail_urban rail rail_electric rail_fast ship" speed="15.39" length="0.95" shape="7013.01,7746.43 7012.88,7746.83 7012.78,7747.10 7012.64,7747.36 7012.40,7747.71"/>
        <lane id=":3389563089_0_1" index="1" disallow="tram rail_urban rail rail_electric rail_fast ship" speed="27.78" length="0.95" shape="7009.95,7745.50 7009.91,7745.63 7009.87,7745.72 7009.82,7745.81 7009.75,7745.92"/>
    </edge>
    <edge id=":3389563091_0" function="internal">
        <lane id=":3389563091_0_0" index="0" allow="private emergency authority army vip passenger hov taxi bus coach delivery truck trailer motorcycle evehicle custom1 custom2" speed="10.22" length="9.91" shape="6958.27,7715.32 6960.91,7715.61 6962.83,7715.82 6964.57,7715.48 6966.66,7714.12"/>
        <lane id=":3389563091_0_1" index="1" allow="private emergency authority army vip passenger hov taxi bus coach delivery truck trailer motorcycle evehicle custom1 custom2" speed="11.34" length="9.91" shape="6958.37,7718.53 6961.63,7718.82 6963.98,7718.92 6966.12,7718.34 6968.70,7716.58"/>
    </edge>
    <edge id=":3389563091_2" function="internal">
        <lane id=":3389563091_2_0" index="0" disallow="tram rail_urban rail rail_electric rail_fast ship" speed="27.78" length="9.86" shape="6960.47,7722.33 6962.03,7719.67 6963.10,7717.82 6964.41,7716.17 6966.66,7714.12"/>
        <lane id=":3389563091_2_1" index="1" disallow="tram rail_urban rail rail_electric rail_fast ship" speed="27.78" length="9.86" shape="6963.19,7724.03 6964.58,7721.62 6965.53,7719.94 6966.68,7718.44 6968.70,7716.58"/>
    </edge>
    <edge id=":3970730290_0" function="internal">
        <lane id=":3970730290_0_0" index="0" allow="private emergency authority army vip passenger hov taxi bus coach delivery truck trailer motorcycle evehicle custom1 custom2" speed="25.00" length="23.37" shape="6962.85,7751.32 6959.28,7745.09 6956.57,7739.26 6954.25,7734.31 6951.83,7730.76"/>
    </edge>
    <edge id=":3970730290_1" function="internal">
        <lane id=":3970730290_1_0" index="0" disallow="tram rail_urban rail rail_electric rail_fast ship" speed="15.27" length="23.62" shape="6962.85,7751.32 6959.81,7745.71 6958.08,7740.02 6957.65,7734.25 6958.53,7728.39"/>
        <lane id=":3970730290_1_1" index="1" disallow="tram rail_urban rail rail_electric rail_fast ship" speed="15.00" length="23.62" shape="6965.51,7749.55 6962.83,7744.43 6961.37,7739.02 6961.13,7733.30 6962.12,7727.29"/>
    </edge>
    <edge id=":474423808#1-AddedOnRampNode_0" function="internal">
        <lane id=":474423808#1-AddedOnRampNode_0_0" index="0" allow="private emergency authority army vip passenger hov taxi bus coach delivery truck trailer motorcycle evehicle custom1 custom2" speed="25.00" length="8.00" shape="7197.70,7866.54 7205.63,7867.62"/>
        <lane id=":474423808#1-AddedOnRampNode_0_1" index="1" allow="private emergency authority army vip passenger hov taxi bus coach delivery truck trailer motorcycle evehicle custom1 custom2" speed="25.00" length="8.00" shape="7197.27,7869.71 7205.20,7870.80"/>
    </edge>
    <edge id=":4955227553_0" function="internal">
        <lane id=":4955227553_0_0" index="0" allow="private emergency authority army vip passenger hov taxi bus coach delivery truck trailer motorcycle evehicle custom1 custom2" speed="25.00" length="8.13" shape="6906.69,7804.04 6909.02,7804.69 6910.72,7804.79 6912.41,7804.92 6914.70,7805.67"/>
        <lane id=":4955227553_0_1" index="1" allow="private emergency authority army vip passenger hov taxi bus coach delivery truck trailer motorcycle evehicle custom1 custom2" speed="25.00" length="8.13" shape="6906.69,7804.04 6908.81,7805.15 6910.07,7806.25 6911.31,7807.39 6913.39,7808.59"/>
        <lane id=":4955227553_0_2" index="2" allow="private emergency authority army vip passenger hov taxi bus coach delivery truck trailer motorcycle evehicle custom1 custom2" speed="25.00" length="8.13" shape="6905.52,7807.01 6907.59,7808.11 6908.82,7809.20 6910.04,7810.33 6912.08,7811.51"/>
    </edge>
    <edge id=":4955227555_0" function="internal">
        <lane id=":4955227555_0_0" index="0" allow="private emergency authority army vip passenger hov taxi bus coach delivery truck trailer motorcycle evehicle custom1 custom2" speed="25.00" length="3.19" shape="7100.95,7853.33 7104.08,7853.79"/>
        <lane id=":4955227555_0_1" index="1" allow="private emergency authority army vip passenger hov taxi bus coach delivery truck trailer motorcycle evehicle custom1 custom2" speed="25.00" length="3.19" shape="7100.46,7856.49 7103.65,7856.96"/>
    </edge>
    <edge id=":4955227555_2" function="internal">
        <lane id=":4955227555_2_0" index="0" allow="private emergency authority army vip passenger hov taxi bus coach delivery truck trailer motorcycle evehicle custom1 custom2" speed="23.61" length="3.10" shape="7101.43,7850.22 7104.51,7850.62"/>
    </edge>
    <edge id=":54379553-AddedOffRampNode_0" function="internal">
        <lane id=":54379553-AddedOffRampNode_0_0" index="0" allow="private emergency authority army vip passenger hov taxi bus coach delivery truck trailer motorcycle evehicle custom1 custom2" speed="22.22" length="12.55" shape="7375.02,7909.21 7372.02,7908.28 7369.52,7907.96 7366.76,7907.94 7362.98,7907.89"/>
        <lane id=":54379553-AddedOffRampNode_0_1" index="1" allow="private emergency authority army vip passenger hov taxi bus coach delivery truck trailer motorcycle evehicle custom1 custom2" speed="22.22" length="12.55" shape="7375.02,7909.21 7372.08,7907.79 7369.70,7906.37 7366.99,7905.24 7363.10,7904.69"/>
    </edge>
    <edge id=":685192542_0" function="internal">
        <lane id=":685192542_0_0" index="0" allow="private emergency authority army vip passenger hov taxi bus coach delivery truck trailer motorcycle evehicle custom1 custom2" speed="22.22" length="8.09" shape="6905.85,7703.09 6908.21,7702.61 6909.81,7702.26 6911.43,7701.98 6913.82,7701.71"/>
    </edge>
    <edge id=":685192542_1" function="internal">
        <lane id=":685192542_1_0" index="0" allow="private emergency authority army vip passenger hov taxi bus coach delivery truck trailer motorcycle evehicle custom1 custom2" speed="18.44" length="4.61" shape="6906.45,7706.23 6907.79,7705.99 6908.73,7705.90 6909.66,7705.95 6911.02,7706.14"/>
        <lane id=":685192542_1_1" index="1" allow="private emergency authority army vip passenger hov taxi bus coach delivery truck trailer motorcycle evehicle custom1 custom2" speed="16.16" length="3.53" shape="6907.04,7709.37 6908.07,7709.19 6908.79,7709.12 6909.50,7709.16 6910.54,7709.31"/>
    </edge>
    <edge id=":685192553_0" function="internal">
        <lane id=":685192553_0_0" index="0" disallow="tram rail_urban rail rail_electric rail_fast ship" speed="14.85" length="9.47" shape="6969.73,7758.35 6967.24,7756.92 6965.73,7755.60 6964.54,7753.94 6962.96,7751.48"/>
        <lane id=":685192553_0_1" index="1" disallow="tram rail_urban rail rail_electric rail_fast ship" speed="14.28" length="9.47" shape="6972.01,7755.93 6969.69,7754.62 6968.26,7753.45 6967.10,7751.96 6965.62,7749.71"/>
    </edge>
    <edge id=":685192553_2" function="internal">
        <lane id=":685192553_2_0" index="0" disallow="tram rail_urban rail rail_electric rail_fast ship" speed="10.69" length="9.47" shape="6962.62,7759.52 6963.15,7757.05 6963.77,7755.26 6963.90,7753.59 6962.96,7751.48"/>
        <lane id=":685192553_2_1" index="1" disallow="tram rail_urban rail rail_electric rail_fast ship" speed="11.92" length="9.47" shape="6965.81,7759.83 6966.38,7756.71 6966.95,7754.46 6966.90,7752.36 6965.62,7749.71"/>
    </edge>
    <edge id=":685192577_0" function="internal">
        <lane id=":685192577_0_0" index="0" allow="private emergency authority army vip passenger hov taxi bus coach delivery truck trailer motorcycle evehicle custom1 custom2" speed="25.00" length="3.27" shape="6862.49,8010.99 6862.90,8010.11 6863.16,8009.50 6863.37,8008.87 6863.64,8007.94"/>
    </edge>
    <edge id=":685192577_1" function="internal">
        <lane id=":685192577_1_0" index="0" disallow="tram rail_urban rail rail_electric rail_fast ship" speed="27.78" length="3.61" shape="6865.38,8012.37 6866.79,8009.15"/>
        <lane id=":685192577_1_1" index="1" disallow="tram rail_urban rail rail_electric rail_fast ship" speed="27.78" length="3.61" shape="6868.27,8013.75 6869.75,8010.35"/>
    </edge>
    <edge id=":685276223_0" function="internal">
        <lane id=":685276223_0_0" index="0" allow="private emergency authority army vip passenger hov taxi bus coach delivery truck trailer motorcycle evehicle custom1 custom2" speed="39.44" length="3.46" shape="6737.83,7713.07 6736.96,7712.41 6736.38,7711.93 6735.83,7711.42 6735.06,7710.64"/>
        <lane id=":685276223_0_1" index="1" allow="private emergency authority army vip passenger hov taxi bus coach delivery truck trailer motorcycle evehicle custom1 custom2" speed="39.44" length="3.46" shape="6739.77,7710.52 6739.00,7709.94 6738.50,7709.53 6738.02,7709.08 6737.34,7708.40"/>
    </edge>
    <edge id=":685276223_2" function="internal">
        <lane id=":685276223_2_0" index="0" allow="private emergency authority army vip passenger hov taxi bus coach delivery truck trailer motorcycle evehicle custom1 custom2" speed="15.97" length="4.19" shape="6736.23,7715.18 6735.11,7714.65 6734.35,7714.25 6733.67,7713.74 6732.78,7712.88"/>
    </edge>
    <edge id=":685276291_0" function="internal">
        <lane id=":685276291_0_0" index="0" allow="private emergency authority army vip passenger hov taxi bus coach delivery truck trailer motorcycle evehicle custom1 custom2" speed="22.22" length="4.87" shape="7204.61,7969.10 7203.18,7969.33 7202.23,7969.58 7201.30,7969.93 7199.96,7970.46"/>
    </edge>
    <edge id=":685276291_1" function="internal">
        <lane id=":685276291_1_0" index="0" allow="private emergency authority army vip passenger hov taxi bus coach delivery truck trailer motorcycle evehicle custom1 custom2" speed="5.08" length="3.65" shape="7204.61,7969.10 7201.17,7969.34 7200.98,7969.28"/>
    </edge>
    <edge id=":685276291_4" function="internal">
        <lane id=":685276291_4_0" index="0" allow="private emergency authority army vip passenger hov taxi bus coach delivery truck trailer motorcycle evehicle custom1 custom2" speed="5.08" length="5.56" shape="7200.98,7969.28 7199.59,7968.85 7199.85,7967.64 7201.97,7965.70"/>
    </edge>
    <edge id=":685276291_2" function="internal">
        <lane id=":685276291_2_0" index="0" allow="private emergency authority army vip passenger hov taxi bus coach delivery truck trailer motorcycle evehicle custom1 custom2" speed="22.22" length="3.64" shape="7198.82,7967.47 7199.82,7967.08 7200.48,7966.75 7201.10,7966.35 7201.97,7965.70"/>
    </edge>
    <edge id=":685276291_3" function="internal">
        <lane id=":685276291_3_0" index="0" disallow="tram rail_urban rail rail_electric rail_fast ship" speed="3.65" length="1.44" shape="7198.82,7967.47 7200.22,7967.79"/>
    </edge>
    <edge id=":685276291_5" function="internal">
        <lane id=":685276291_5_0" index="0" disallow="tram rail_urban rail rail_electric rail_fast ship" speed="3.65" length="3.23" shape="7200.22,7967.79 7200.88,7968.40 7200.79,7969.29 7199.96,7970.46"/>
    </edge>
    <edge id=":685276345_0" function="internal">
        <lane id=":685276345_0_0" index="0" allow="private emergency authority army vip passenger hov taxi bus coach delivery truck trailer motorcycle evehicle custom1 custom2" speed="30.83" length="3.08" shape="7378.17,7910.10 7377.26,7909.97 7376.66,7909.83 7376.06,7909.61 7375.21,7909.28"/>
    </edge>
    <edge id=":685276345_1" function="internal">
        <lane id=":685276345_1_0" index="0" allow="private emergency authority army vip passenger hov taxi bus coach delivery truck trailer motorcycle evehicle custom1 custom2" speed="39.44" length="3.42" shape="7378.54,7906.92 7374.75,7906.39"/>
        <lane id=":685276345_1_1" index="1" allow="private emergency authority army vip passenger hov taxi bus coach delivery truck trailer motorcycle evehicle custom1 custom2" speed="39.44" length="3.42" shape="7378.91,7903.74 7375.93,7903.34"/>
    </edge>
    <edge id=":685276959_0" function="internal">
        <lane id=":685276959_0_0" index="0" allow="private emergency authority army vip passenger hov taxi bus coach delivery truck trailer motorcycle evehicle custom1 custom2" speed="30.83" length="2.92" shape="7046.38,7862.55 7043.50,7862.03"/>
    </edge>
    <edge id=":685276959_1" function="internal">
        <lane id=":685276959_1_0" index="0" allow="private emergency authority army vip passenger hov taxi bus coach delivery truck trailer motorcycle evehicle custom1 custom2" speed="39.44" length="2.46" shape="7046.75,7859.34 7045.98,7859.25 7045.46,7859.17 7044.94,7859.07 7044.18,7858.90"/>
        <lane id=":685276959_1_1" index="1" allow="private emergency authority army vip passenger hov taxi bus coach delivery truck trailer motorcycle evehicle custom1 custom2" speed="39.44" length="2.46" shape="7047.13,7856.16 7046.45,7856.08 7045.98,7856.01 7045.52,7855.92 7044.85,7855.78"/>
    </edge>
    <edge id=":95117787#2-AddedOnRampNode_0" function="internal">
        <lane id=":95117787#2-AddedOnRampNode_0_0" index="0" allow="private emergency authority army vip passenger hov taxi bus coach delivery truck trailer motorcycle evehicle custom1 custom2" speed="39.44" length="8.00" shape="6952.41,7834.96 6944.80,7832.50"/>
        <lane id=":95117787#2-AddedOnRampNode_0_1" index="1" allow="private emergency authority army vip passenger hov taxi bus coach delivery truck trailer motorcycle evehicle custom1 custom2" speed="39.44" length="8.00" shape="6953.39,7831.91 6945.78,7829.46"/>
    </edge>
    <edge id=":95841103#1-AddedOnRampNode_0" function="internal">
        <lane id=":95841103#1-AddedOnRampNode_0_0" index="0" allow="private emergency authority army vip passenger hov taxi bus coach delivery truck trailer motorcycle evehicle custom1 custom2" speed="39.44" length="0.32" shape="6666.66,7639.64 6666.47,7639.38"/>
        <lane id=":95841103#1-AddedOnRampNode_0_1" index="1" allow="private emergency authority army vip passenger hov taxi bus coach delivery truck trailer motorcycle evehicle custom1 custom2" speed="39.44" length="0.32" shape="6669.22,7637.72 6669.03,7637.46"/>
        <lane id=":95841103#1-AddedOnRampNode_0_2" index="2" allow="private emergency authority army vip passenger hov taxi bus coach delivery truck trailer motorcycle evehicle custom1 custom2" speed="39.44" length="0.32" shape="6671.78,7635.80 6671.60,7635.55"/>
    </edge>

    <edge id="-98835887" from="1143316916" to="685276291" name="Rua António Sampaio (Pintor)" priority="10" type="highway.tertiary" shape="7090.41,8002.21 7164.12,7982.39 7195.89,7970.30">
        <lane id="-98835887_0" index="0" disallow="tram rail_urban rail rail_electric rail_fast ship" speed="22.22" length="113.90" shape="7089.99,8000.66 7163.63,7980.87 7198.82,7967.47">
            <param key="origId" value="98835887"/>
        </lane>
    </edge>
    <edge id="1010075428" from="1110673494" to="685276291" priority="9" type="highway.motorway_link" spreadType="center" shape="7263.23,7898.51 7258.55,7897.01 7249.16,7901.76 7241.77,7910.95 7238.42,7919.46 7233.61,7945.39 7226.18,7957.46 7216.23,7965.37 7205.26,7969.01 7195.89,7970.30">
        <lane id="1010075428_0" index="0" allow="private emergency authority army vip passenger hov taxi bus coach delivery truck trailer motorcycle evehicle custom1 custom2" speed="22.22" length="99.30" shape="7260.80,7897.73 7258.55,7897.01 7249.16,7901.76 7241.77,7910.95 7238.42,7919.46 7233.61,7945.39 7226.18,7957.46 7216.23,7965.37 7205.26,7969.01 7204.61,7969.10">
            <param key="origId" value="1010075428"/>
        </lane>
    </edge>
    <edge id="1067636645" from="1110673725" to="685276959" name="Via de Cintura Interna" priority="9" type="highway.motorway_link" spreadType="center" shape="7156.74,7881.58 7143.05,7877.11 7044.73,7862.30">
        <lane id="1067636645_0" index="0" allow="private emergency authority army vip passenger hov taxi bus coach delivery truck trailer motorcycle evehicle custom1 custom2" speed="22.22" length="110.46" shape="7155.12,7881.05 7143.05,7877.11 7046.38,7862.55">
            <param key="origId" value="1067636645"/>
        </lane>
    </edge>
    <edge id="331866644#1" from="685192553" to="3970730290" priority="12" type="highway.primary" spreadType="center">
        <lane id="331866644#1_0" index="0" disallow="tram rail_urban rail rail_electric rail_fast ship" speed="27.78" length="0.20" shape="6962.96,7751.48 6962.85,7751.32">
            <param key="origId" value="331866644"/>
        </lane>
        <lane id="331866644#1_1" index="1" disallow="tram rail_urban rail rail_electric rail_fast ship" speed="27.78" length="0.20" shape="6965.62,7749.71 6965.51,7749.55">
            <param key="origId" value="331866644"/>
        </lane>
    </edge>
    <edge id="331866644#2" from="3970730290" to="3389563091" priority="12" type="highway.primary" spreadType="center" shape="6962.52,7747.93 6959.66,7740.20 6959.25,7731.98 6961.32,7724.00 6965.68,7717.01">
        <lane id="331866644#2_0" index="0" disallow="tram rail_urban rail rail_electric rail_fast ship" speed="27.78" length="4.93" shape="6958.53,7728.39 6959.83,7723.36 6960.47,7722.33">
            <param key="origId" value="331866644"/>
        </lane>
        <lane id="331866644#2_1" index="1" disallow="tram rail_urban rail rail_electric rail_fast ship" speed="27.78" length="4.93" shape="6962.12,7727.29 6962.81,7724.64 6963.19,7724.03">
            <param key="origId" value="331866644"/>
        </lane>
    </edge>
    <edge id="331866644#3" from="3389563091" to="3389563082" priority="12" type="highway.primary" spreadType="center" shape="6965.68,7717.01 6972.83,7711.09 6981.55,7707.88">
        <lane id="331866644#3_0" index="0" disallow="tram rail_urban rail rail_electric rail_fast ship" speed="27.78" length="13.84" shape="6966.66,7714.12 6972.02,7709.68 6978.99,7707.12">
            <param key="origId" value="331866644"/>
        </lane>
        <lane id="331866644#3_1" index="1" disallow="tram rail_urban rail rail_electric rail_fast ship" speed="27.78" length="13.84" shape="6968.70,7716.58 6973.64,7712.50 6980.10,7710.12">
            <param key="origId" value="331866644"/>
        </lane>
    </edge>
    <edge id="331866644#4" from="3389563082" to="3389563088" priority="12" type="highway.primary" spreadType="center" shape="6981.55,7707.88 6990.83,7707.77 6999.63,7710.74 7006.92,7716.47">
        <lane id="331866644#4_0" index="0" disallow="tram rail_urban rail rail_electric rail_fast ship" speed="27.78" length="17.51" shape="6991.33,7706.25 7000.40,7709.31 7007.51,7714.90">
            <param key="origId" value="331866644"/>
        </lane>
        <lane id="331866644#4_1" index="1" disallow="tram rail_urban rail rail_electric rail_fast ship" speed="27.78" length="17.51" shape="6991.34,7709.63 6998.86,7712.17 7005.53,7717.41">
            <param key="origId" value="331866644"/>
        </lane>
    </edge>
    <edge id="331866644#5" from="3389563088" to="3389563089" priority="12" type="highway.primary" spreadType="center" shape="7006.92,7716.47 7011.36,7723.13 7013.68,7730.78 7013.67,7738.77 7011.34,7746.42">
        <lane id="331866644#5_0" index="0" disallow="tram rail_urban rail rail_electric rail_fast ship" speed="27.78" length="31.00" shape="7008.53,7716.01 7012.82,7722.44 7015.28,7730.54 7015.27,7739.01 7013.01,7746.43">
            <param key="origId" value="331866644"/>
        </lane>
        <lane id="331866644#5_1" index="1" disallow="tram rail_urban rail rail_electric rail_fast ship" speed="27.78" length="31.00" shape="7005.87,7717.78 7009.90,7723.82 7012.08,7731.02 7012.07,7738.53 7009.95,7745.50">
            <param key="origId" value="331866644"/>
        </lane>
    </edge>
    <edge id="331866644#6" from="3389563089" to="3389563087" priority="12" type="highway.primary" spreadType="center" shape="7011.34,7746.42 7006.85,7753.11 7000.59,7758.21 6993.12,7761.28">
        <lane id="331866644#6_0" index="0" disallow="tram rail_urban rail rail_electric rail_fast ship" speed="27.78" length="21.76" shape="7012.40,7747.71 7008.05,7754.20 7001.42,7759.60 6995.55,7762.01">
            <param key="origId" value="331866644"/>
        </lane>
        <lane id="331866644#6_1" index="1" disallow="tram rail_urban rail rail_electric rail_fast ship" speed="27.78" length="21.76" shape="7009.75,7745.92 7005.65,7752.02 6999.76,7756.82 6994.34,7759.05">
            <param key="origId" value="331866644"/>
        </lane>
    </edge>
    <edge id="331866644#7" from="3389563087" to="685192553" priority="12" type="highway.primary" spreadType="center" shape="6993.12,7761.28 6985.32,7762.04 6977.63,7760.59 6970.66,7757.03 6964.99,7751.65">
        <lane id="331866644#7_0" index="0" disallow="tram rail_urban rail rail_electric rail_fast ship" speed="27.78" length="9.29" shape="6979.45,7762.56 6977.11,7762.12 6969.73,7758.35">
            <param key="origId" value="331866644"/>
        </lane>
        <lane id="331866644#7_1" index="1" disallow="tram rail_urban rail rail_electric rail_fast ship" speed="27.78" length="9.29" shape="6979.15,7759.25 6978.15,7759.06 6972.01,7755.93">
            <param key="origId" value="331866644"/>
        </lane>
    </edge>
    <edge id="331868361#0" from="269354454" to="331868361#0-AddedOffRampNode" name="Nó da Barrosa" priority="9" type="highway.motorway_link" spreadType="center" shape="6743.90,7692.57 6772.17,7714.47 6797.22,7722.31 6814.92,7723.78">
        <lane id="331868361#0_0" index="0" allow="private emergency authority army vip passenger hov taxi bus coach delivery truck trailer motorcycle evehicle custom1 custom2" speed="22.22" length="74.09" shape="6745.23,7693.60 6772.17,7714.47 6797.22,7722.31 6810.93,7723.45">
            <param key="origId" value="331868361"/>
        </lane>
    </edge>
    <edge id="331868361#0-AddedOffRampEdge" from="331868361#0-AddedOffRampNode" to="685192542" name="Nó da Barrosa" priority="9" type="highway.motorway_link" spreadType="center" shape="6815.18,7720.59 6818.10,7720.83 6842.32,7718.40 6912.93,7705.00">
        <lane id="331868361#0-AddedOffRampEdge_0" index="0" allow="private emergency authority army vip passenger hov taxi bus coach delivery truck trailer motorcycle evehicle custom1 custom2" speed="22.22" length="88.54" shape="6819.43,7717.48 6841.86,7715.23 6905.85,7703.09">
            <param key="origId" value="331868361"/>
        </lane>
        <lane id="331868361#0-AddedOffRampEdge_1" index="1" allow="private emergency authority army vip passenger hov taxi bus coach delivery truck trailer motorcycle evehicle custom1 custom2" speed="22.22" length="88.54" shape="6819.17,7720.72 6842.32,7718.40 6906.45,7706.23">
            <param key="origId" value="331868361"/>
        </lane>
        <lane id="331868361#0-AddedOffRampEdge_2" index="2" allow="private emergency authority army vip passenger hov taxi bus coach delivery truck trailer motorcycle evehicle custom1 custom2" speed="22.22" length="88.54" shape="6818.90,7723.97 6842.78,7721.57 6907.04,7709.37">
            <param key="origId" value="331868361"/>
        </lane>
    </edge>
    <edge id="331868361#1" from="685192542" to="1131360770" name="Nó da Barrosa" priority="9" type="highway.motorway_link" spreadType="center" shape="6912.33,7701.85 6956.68,7697.69 6977.15,7687.14 6989.90,7675.06 7002.24,7660.91 7007.72,7641.25">
        <lane id="331868361#1_0" index="0" allow="private emergency authority army vip passenger hov taxi bus coach delivery truck trailer motorcycle evehicle custom1 custom2" speed="22.22" length="122.37" shape="6913.82,7701.71 6956.68,7697.69 6977.15,7687.14 6989.90,7675.06 7002.24,7660.91 7007.60,7641.69">
            <param key="origId" value="331868361"/>
        </lane>
    </edge>
    <edge id="332557431-AddedOnRampEdge" from="1110673649" to="332557431-AddedOnRampNode" name="Via Engenheiro Edgar Cardoso" priority="12" type="highway.primary" spreadType="center" shape="6893.36,7975.70 6878.93,8018.72 6856.64,8068.76">
        <lane id="332557431-AddedOnRampEdge_0" index="0" disallow="tram rail_urban rail rail_electric rail_fast ship" speed="27.78" length="98.71" acceleration="1" shape="6895.94,7978.09 6881.92,8019.88 6859.56,8070.06">
            <param key="origId" value="332557431 95365326"/>
        </lane>
        <lane id="332557431-AddedOnRampEdge_1" index="1" disallow="tram rail_urban rail rail_electric rail_fast ship" speed="27.78" length="98.71" shape="6892.90,7977.07 6878.93,8018.72 6856.64,8068.76">
            <param key="origId" value="332557431 95365326"/>
        </lane>
        <lane id="332557431-AddedOnRampEdge_2" index="2" disallow="tram rail_urban rail rail_electric rail_fast ship" speed="27.78" length="98.71" shape="6889.87,7976.05 6875.94,8017.56 6853.72,8067.46">
            <param key="origId" value="332557431 95365326"/>
        </lane>
    </edge>
    <edge id="394028171" from="3970730290" to="4955227555" name="Nó da Barrosa" priority="9" type="highway.motorway_link" spreadType="center" shape="6962.52,7747.93 6955.42,7734.45 6949.95,7728.82 6942.72,7724.18 6933.75,7719.30 6920.64,7716.58 6907.26,7718.46 6895.58,7724.95 6886.06,7733.38 6880.16,7745.73 6878.39,7757.70 6879.62,7766.51 6884.71,7780.55 6895.72,7792.01 6909.40,7799.07 6943.90,7812.03 6951.88,7815.03 6959.38,7817.85 6969.60,7821.69 7006.57,7831.92 7058.46,7843.02 7075.04,7847.01 7103.02,7850.41">
        <lane id="394028171_0" index="0" allow="private emergency authority army vip passenger hov taxi bus coach delivery truck trailer motorcycle evehicle custom1 custom2" speed="22.22" length="354.76" shape="6951.83,7730.76 6949.95,7728.82 6942.72,7724.18 6933.75,7719.30 6920.64,7716.58 6907.26,7718.46 6895.58,7724.95 6886.06,7733.38 6880.16,7745.73 6878.39,7757.70 6879.62,7766.51 6884.71,7780.55 6895.72,7792.01 6909.40,7799.07 6943.90,7812.03 6951.88,7815.03 6959.38,7817.85 6969.60,7821.69 7006.57,7831.92 7058.46,7843.02 7075.04,7847.01 7101.43,7850.22">
            <param key="origId" value="394028171 1067636643 1067636644 1067636642"/>
        </lane>
    </edge>
    <edge id="474423808#0" from="269354459" to="4955227555" name="Via de Cintura Interna" priority="14" type="highway.motorway" spreadType="center">
        <lane id="474423808#0_0" index="0" allow="private emergency authority army vip passenger hov taxi bus coach delivery truck trailer motorcycle evehicle custom1 custom2" speed="25.00" length="53.65" shape="7047.93,7845.08 7100.95,7853.33">
            <param key="origId" value="474423808"/>
        </lane>
        <lane id="474423808#0_1" index="1" allow="private emergency authority army vip passenger hov taxi bus coach delivery truck trailer motorcycle evehicle custom1 custom2" speed="25.00" length="53.65" shape="7047.44,7848.24 7100.46,7856.49">
            <param key="origId" value="474423808"/>
        </lane>
        <param key="ref" value="A 44"/>
    </edge>
    <edge id="474423808#1" from="474423808#1-AddedOnRampNode" to="1103406302" name="Via de Cintura Interna" priority="14" type="highway.motorway" spreadType="center" shape="7201.45,7868.67 7235.45,7873.30 7295.21,7881.96 7386.32,7895.19 7435.35,7902.12">
        <lane id="474423808#1_0" index="0" allow="private emergency authority army vip passenger hov taxi bus coach delivery truck trailer motorcycle evehicle custom1 custom2" speed="25.00" length="232.28" shape="7205.63,7867.62 7235.67,7871.72 7295.44,7880.38 7386.55,7893.61 7435.57,7900.54">
            <param key="origId" value="474423808 263739117"/>
        </lane>
        <lane id="474423808#1_1" index="1" allow="private emergency authority army vip passenger hov taxi bus coach delivery truck trailer motorcycle evehicle custom1 custom2" speed="25.00" length="232.28" shape="7205.20,7870.80 7235.23,7874.88 7294.98,7883.54 7386.09,7896.77 7435.13,7903.70">
            <param key="origId" value="474423808 263739117"/>
        </lane>
        <param key="ref" value="A 44"/>
    </edge>
    <edge id="474423808#1-AddedOnRampEdge" from="4955227555" to="474423808#1-AddedOnRampNode" name="Via de Cintura Interna" priority="14" type="highway.motorway" spreadType="center" shape="7102.58,7853.59 7201.67,7867.08">
        <lane id="474423808#1-AddedOnRampEdge_0" index="0" allow="private emergency authority army vip passenger hov taxi bus coach delivery truck trailer motorcycle evehicle custom1 custom2" speed="25.00" length="94.49" acceleration="1" shape="7104.51,7850.62 7198.14,7863.37">
            <param key="origId" value="474423808 263739117"/>
        </lane>
        <lane id="474423808#1-AddedOnRampEdge_1" index="1" allow="private emergency authority army vip passenger hov taxi bus coach delivery truck trailer motorcycle evehicle custom1 custom2" speed="25.00" length="94.49" shape="7104.08,7853.79 7197.70,7866.54">
            <param key="origId" value="474423808 263739117"/>
        </lane>
        <lane id="474423808#1-AddedOnRampEdge_2" index="2" allow="private emergency authority army vip passenger hov taxi bus coach delivery truck trailer motorcycle evehicle custom1 custom2" speed="25.00" length="94.49" shape="7103.65,7856.96 7197.27,7869.71">
            <param key="origId" value="474423808 263739117"/>
        </lane>
        <param key="ref" value="A 44"/>
    </edge>
    <edge id="474423809" from="4955227553" to="269354459" name="Via de Cintura Interna" priority="14" type="highway.motorway" spreadType="center" shape="6909.78,7806.98 6927.53,7814.91 6974.59,7829.75 7043.88,7846.07">
        <lane id="474423809_0" index="0" allow="private emergency authority army vip passenger hov taxi bus coach delivery truck trailer motorcycle evehicle custom1 custom2" speed="25.00" length="132.17" shape="6914.70,7805.67 6928.67,7811.91 6975.44,7826.66 7040.86,7842.07">
            <param key="origId" value="474423809 95841129 95841109"/>
        </lane>
        <lane id="474423809_1" index="1" allow="private emergency authority army vip passenger hov taxi bus coach delivery truck trailer motorcycle evehicle custom1 custom2" speed="25.00" length="132.17" shape="6913.39,7808.59 6927.53,7814.91 6974.59,7829.75 7040.13,7845.19">
            <param key="origId" value="474423809 95841129 95841109"/>
        </lane>
        <lane id="474423809_2" index="2" allow="private emergency authority army vip passenger hov taxi bus coach delivery truck trailer motorcycle evehicle custom1 custom2" speed="25.00" length="132.17" shape="6912.08,7811.51 6926.39,7817.91 6973.74,7832.84 7039.40,7848.30">
            <param key="origId" value="474423809 95841129 95841109"/>
        </lane>
        <param key="ref" value="A 44"/>
    </edge>
    <edge id="474423810" from="1147305736" to="269354454" name="Via de Cintura Interna" priority="14" type="highway.motorway" spreadType="center" shape="6632.78,7547.04 6673.37,7614.18 6695.32,7642.61 6741.51,7694.69">
        <lane id="474423810_0" index="0" allow="private emergency authority army vip passenger hov taxi bus coach delivery truck trailer motorcycle evehicle custom1 custom2" speed="25.00" length="182.36" acceleration="1" shape="6635.52,7545.38 6676.01,7612.37 6697.79,7640.57 6742.83,7691.35">
            <param key="origId" value="474423810"/>
        </lane>
        <lane id="474423810_1" index="1" allow="private emergency authority army vip passenger hov taxi bus coach delivery truck trailer motorcycle evehicle custom1 custom2" speed="25.00" length="182.36" shape="6632.78,7547.04 6673.37,7614.18 6695.32,7642.61 6740.43,7693.48">
            <param key="origId" value="474423810"/>
        </lane>
        <lane id="474423810_2" index="2" allow="private emergency authority army vip passenger hov taxi bus coach delivery truck trailer motorcycle evehicle custom1 custom2" speed="25.00" length="182.36" shape="6630.04,7548.70 6670.73,7615.99 6692.85,7644.65 6738.04,7695.60">
            <param key="origId" value="474423810"/>
        </lane>
        <param key="ref" value="A 44"/>
    </edge>
    <edge id="505635971" from="3389563082" to="1131360770" name="Via Engenheiro Edgar Cardoso" priority="12" type="highway.primary" spreadType="center" shape="6981.55,7707.88 6988.63,7701.33 6993.63,7693.50 6999.07,7681.97 7003.97,7667.50 7012.21,7642.95">
        <lane id="505635971_0" index="0" disallow="tram rail_urban rail rail_electric rail_fast ship" speed="27.78" length="62.96" shape="6987.59,7699.98 6992.23,7692.72 6997.58,7681.37 7002.45,7666.99 7010.64,7642.60">
            <param key="origId" value="505635971"/>
        </lane>
        <lane id="505635971_1" index="1" disallow="tram rail_urban rail rail_electric rail_fast ship" speed="27.78" length="62.96" shape="6989.84,7702.39 6995.03,7694.28 7000.56,7682.57 7005.49,7668.01 7013.73,7643.46">
            <param key="origId" value="505635971"/>
        </lane>
    </edge>
    <edge id="54379491" from="685192577" to="685276223" name="Nó da Barrosa" priority="9" type="highway.motorway_link" spreadType="center" shape="6863.20,8009.50 6874.56,7969.52 6876.67,7927.24 6872.15,7894.18 6861.80,7860.88 6848.11,7835.48 6822.58,7801.72 6775.04,7753.23 6741.67,7717.74 6733.99,7714.12">
        <lane id="54379491_0" index="0" allow="private emergency authority army vip passenger hov taxi bus coach delivery truck trailer motorcycle evehicle custom1 custom2" speed="22.22" length="344.33" shape="6863.64,8007.94 6874.56,7969.52 6876.67,7927.24 6872.15,7894.18 6861.80,7860.88 6848.11,7835.48 6822.58,7801.72 6775.04,7753.23 6741.67,7717.74 6736.23,7715.18">
            <param key="origId" value="54379491"/>
        </lane>
    </edge>
    <edge id="54379553" from="685276345" to="54379553-AddedOffRampNode" priority="9" type="highway.motorway_link" spreadType="center" shape="7377.04,7909.97 7363.10,7904.69">
        <lane id="54379553_0" index="0" allow="private emergency authority army vip passenger hov taxi bus coach delivery truck trailer motorcycle evehicle custom1 custom2" speed="22.22" length="0.20" shape="7375.21,7909.28 7375.02,7909.21">
            <param key="origId" value="54379553"/>
        </lane>
    </edge>
    <edge id="54379553-AddedOffRampEdge" from="54379553-AddedOffRampNode" to="1110673494" priority="9" type="highway.motorway_link" spreadType="center" shape="7363.04,7906.29 7341.94,7905.55 7263.41,7896.92">
        <lane id="54379553-AddedOffRampEdge_0" index="0" allow="private emergency authority army vip passenger hov taxi bus coach delivery truck trailer motorcycle evehicle custom1 custom2" speed="22.22" length="98.97" shape="7362.98,7907.89 7341.82,7907.15 7264.38,7898.64">
            <param key="origId" value="54379553"/>
        </lane>
        <lane id="54379553-AddedOffRampEdge_1" index="1" allow="private emergency authority army vip passenger hov taxi bus coach delivery truck trailer motorcycle evehicle custom1 custom2" speed="22.22" length="98.97" shape="7363.10,7904.69 7342.06,7903.95 7264.73,7895.46">
            <param key="origId" value="54379553"/>
        </lane>
    </edge>
    <edge id="546895481-AddedOffRampEdge" from="546895481-AddedOffRampNode" to="685192577" name="Via Engenheiro Edgar Cardoso" priority="12" type="highway.primary" spreadType="center" shape="6821.31,8100.14 6837.37,8070.99 6866.09,8010.88">
        <lane id="546895481-AddedOffRampEdge_0" index="0" disallow="tram rail_urban rail rail_electric rail_fast ship" speed="27.78" length="98.25" shape="6818.51,8098.60 6834.52,8069.53 6862.49,8010.99">
            <param key="origId" value="546895481 548110440 548110441 548110451 548110452 95365324"/>
        </lane>
        <lane id="546895481-AddedOffRampEdge_1" index="1" disallow="tram rail_urban rail rail_electric rail_fast ship" speed="27.78" length="98.25" shape="6821.31,8100.14 6837.37,8070.99 6865.38,8012.37">
            <param key="origId" value="546895481 548110440 548110441 548110451 548110452 95365324"/>
        </lane>
        <lane id="546895481-AddedOffRampEdge_2" index="2" disallow="tram rail_urban rail rail_electric rail_fast ship" speed="27.78" length="98.25" shape="6824.11,8101.68 6840.22,8072.45 6868.27,8013.75">
            <param key="origId" value="546895481 548110440 548110441 548110451 548110452 95365324"/>
        </lane>
        <param key="origFrom" value="1106015726"/>
    </edge>
    <edge id="95117787#0" from="1103406460" to="685276345" name="Via de Cintura Interna" priority="14" type="highway.motorway" spreadType="center" shape="7433.16,7913.31 7377.41,7906.79">
        <lane id="95117787#0_0" index="0" allow="private emergency authority army vip passenger hov taxi bus coach delivery truck trailer motorcycle evehicle custom1 custom2" speed="39.44" length="55.00" shape="7432.79,7916.49 7378.17,7910.10">
            <param key="origId" value="95117787"/>
        </lane>
        <lane id="95117787#0_1" index="1" allow="private emergency authority army vip passenger hov taxi bus coach delivery truck trailer motorcycle evehicle custom1 custom2" speed="39.44" length="55.00" shape="7433.16,7913.31 7378.54,7906.92">
            <param key="origId" value="95117787"/>
        </lane>
        <lane id="95117787#0_2" index="2" allow="private emergency authority army vip passenger hov taxi bus coach delivery truck trailer motorcycle evehicle custom1 custom2" speed="39.44" length="55.00" shape="7433.53,7910.13 7378.91,7903.74">
            <param key="origId" value="95117787"/>
        </lane>
        <param key="ref" value="A 44"/>
    </edge>
    <edge id="95117787#1" from="685276345" to="685276959" name="Via de Cintura Interna" priority="14" type="highway.motorway" spreadType="center" shape="7377.60,7905.21 7242.66,7884.65 7167.64,7873.67 7097.66,7863.68 7045.74,7857.61">
        <lane id="95117787#1_0" index="0" allow="private emergency authority army vip passenger hov taxi bus coach delivery truck trailer motorcycle evehicle custom1 custom2" speed="39.44" length="331.78" shape="7374.75,7906.39 7242.42,7886.23 7167.41,7875.25 7097.45,7865.27 7046.75,7859.34">
            <param key="origId" value="95117787"/>
        </lane>
        <lane id="95117787#1_1" index="1" allow="private emergency authority army vip passenger hov taxi bus coach delivery truck trailer motorcycle evehicle custom1 custom2" speed="39.44" length="331.78" shape="7375.93,7903.34 7242.90,7883.07 7167.87,7872.09 7097.87,7862.09 7047.13,7856.16">
            <param key="origId" value="95117787"/>
        </lane>
        <param key="ref" value="A 44"/>
    </edge>
    <edge id="95117787#2" from="95117787#2-AddedOnRampNode" to="685276223" name="Via de Cintura Interna" priority="14" type="highway.motorway" spreadType="center" shape="6949.10,7832.21 6923.54,7823.97 6881.50,7805.74 6817.00,7769.90 6782.93,7744.99 6737.41,7710.75">
        <lane id="95117787#2_0" index="0" allow="private emergency authority army vip passenger hov taxi bus coach delivery truck trailer motorcycle evehicle custom1 custom2" speed="39.44" length="239.89" shape="6944.80,7832.50 6922.97,7825.47 6880.79,7807.18 6816.14,7771.25 6781.98,7746.28 6737.83,7713.07">
            <param key="origId" value="95117787 95841139 95841103"/>
        </lane>
        <lane id="95117787#2_1" index="1" allow="private emergency authority army vip passenger hov taxi bus coach delivery truck trailer motorcycle evehicle custom1 custom2" speed="39.44" length="239.89" shape="6945.78,7829.46 6924.11,7822.47 6882.21,7804.30 6817.86,7768.55 6783.88,7743.70 6739.77,7710.52">
            <param key="origId" value="95117787 95841139 95841103"/>
        </lane>
        <param key="ref" value="A 44"/>
    </edge>
    <edge id="95117787#2-AddedOnRampEdge" from="685276959" to="95117787#2-AddedOnRampNode" name="Via de Cintura Interna" priority="14" type="highway.motorway" spreadType="center" shape="7045.41,7859.17 7009.93,7851.51 6969.55,7840.48 6948.60,7833.73">
        <lane id="95117787#2-AddedOnRampEdge_0" index="0" allow="private emergency authority army vip passenger hov taxi bus coach delivery truck trailer motorcycle evehicle custom1 custom2" speed="39.44" length="94.90" acceleration="1" shape="7043.50,7862.03 7009.17,7854.62 6968.64,7843.55 6951.43,7838.00">
            <param key="origId" value="95117787 95841139 95841103"/>
        </lane>
        <lane id="95117787#2-AddedOnRampEdge_1" index="1" allow="private emergency authority army vip passenger hov taxi bus coach delivery truck trailer motorcycle evehicle custom1 custom2" speed="39.44" length="94.90" shape="7044.18,7858.90 7009.93,7851.51 6969.55,7840.48 6952.41,7834.96">
            <param key="origId" value="95117787 95841139 95841103"/>
        </lane>
        <lane id="95117787#2-AddedOnRampEdge_2" index="2" allow="private emergency authority army vip passenger hov taxi bus coach delivery truck trailer motorcycle evehicle custom1 custom2" speed="39.44" length="94.90" shape="7044.85,7855.78 7010.69,7848.40 6970.46,7837.41 6953.39,7831.91">
            <param key="origId" value="95117787 95841139 95841103"/>
        </lane>
        <param key="ref" value="A 44"/>
    </edge>
    <edge id="95362523" from="269354454" to="4955227553" name="Via de Cintura Interna" priority="14" type="highway.motorway" spreadType="center" shape="6740.31,7695.75 6753.15,7709.80 6778.11,7730.79 6822.43,7762.97 6886.17,7797.63 6909.78,7806.98">
        <lane id="95362523_0" index="0" allow="private emergency authority army vip passenger hov taxi bus coach delivery truck trailer motorcycle evehicle custom1 custom2" speed="25.00" length="198.67" shape="6742.66,7695.95 6754.26,7708.64 6779.10,7729.53 6823.29,7761.61 6886.85,7796.18 6906.69,7804.04">
            <param key="origId" value="95362523"/>
        </lane>
        <lane id="95362523_1" index="1" allow="private emergency authority army vip passenger hov taxi bus coach delivery truck trailer motorcycle evehicle custom1 custom2" speed="25.00" length="198.67" shape="6740.30,7698.11 6752.04,7710.96 6777.12,7732.05 6821.57,7764.33 6885.49,7799.08 6905.52,7807.01">
            <param key="origId" value="95362523"/>
        </lane>
        <param key="ref" value="A 44"/>
    </edge>
    <edge id="95365322" from="685192577" to="685192553" name="Via Engenheiro Edgar Cardoso" priority="12" type="highway.primary" spreadType="center" shape="6867.53,8011.57 6957.02,7791.02 6963.77,7764.31 6964.99,7751.65">
        <lane id="95365322_0" index="0" disallow="tram rail_urban rail rail_electric rail_fast ship" speed="27.78" length="268.26" shape="6866.79,8009.15 6955.50,7790.52 6962.19,7764.04 6962.62,7759.52">
            <param key="origId" value="95365322"/>
        </lane>
        <lane id="95365322_1" index="1" disallow="tram rail_urban rail rail_electric rail_fast ship" speed="27.78" length="268.26" shape="6869.75,8010.35 6958.54,7791.52 6965.35,7764.58 6965.81,7759.83">
            <param key="origId" value="95365322"/>
        </lane>
    </edge>
    <edge id="95365325" from="3389563087" to="1110673649" name="Via Engenheiro Edgar Cardoso" priority="12" type="highway.primary" spreadType="center" shape="6993.12,7761.28 6979.10,7769.32 6972.54,7777.82 6942.97,7844.24 6922.94,7894.40 6891.84,7975.19">
        <lane id="95365325_0" index="0" disallow="tram rail_urban rail rail_electric rail_fast ship" speed="27.78" length="225.14" shape="6982.17,7769.41 6980.17,7770.55 6973.92,7778.65 6944.44,7844.86 6924.43,7894.98 6893.87,7974.37">
            <param key="origId" value="95365325"/>
        </lane>
        <lane id="95365325_1" index="1" disallow="tram rail_urban rail rail_electric rail_fast ship" speed="27.78" length="225.14" shape="6980.57,7766.63 6978.03,7768.09 6971.16,7776.99 6941.50,7843.62 6921.45,7893.82 6890.89,7973.22">
            <param key="origId" value="95365325"/>
        </lane>
    </edge>
    <edge id="95841103#1" from="95841103#1-AddedOnRampNode" to="269355962" name="Via de Cintura Interna" priority="14" type="highway.motorway" spreadType="center" shape="6669.12,7637.58 6639.75,7598.22 6618.21,7559.80">
        <lane id="95841103#1_0" index="0" allow="private emergency authority army vip passenger hov taxi bus coach delivery truck trailer motorcycle evehicle custom1 custom2" speed="39.44" length="93.01" shape="6666.47,7639.38 6637.06,7599.97 6615.42,7561.36">
            <param key="origId" value="95841103"/>
        </lane>
        <lane id="95841103#1_1" index="1" allow="private emergency authority army vip passenger hov taxi bus coach delivery truck trailer motorcycle evehicle custom1 custom2" speed="39.44" length="93.01" shape="6669.03,7637.46 6639.75,7598.22 6618.21,7559.80">
            <param key="origId" value="95841103"/>
        </lane>
        <lane id="95841103#1_2" index="2" allow="private emergency authority army vip passenger hov taxi bus coach delivery truck trailer motorcycle evehicle custom1 custom2" speed="39.44" length="93.01" shape="6671.60,7635.55 6642.44,7596.47 6621.00,7558.23">
            <param key="origId" value="95841103"/>
        </lane>
        <param key="ref" value="A 44"/>
    </edge>
    <edge id="95841103#1-AddedOnRampEdge" from="685276223" to="95841103#1-AddedOnRampNode" name="Via de Cintura Interna" priority="14" type="highway.motorway" spreadType="center" shape="6736.27,7711.87 6703.19,7678.20 6669.96,7638.70 6669.12,7637.58">
        <lane id="95841103#1-AddedOnRampEdge_0" index="0" allow="private emergency authority army vip passenger hov taxi bus coach delivery truck trailer motorcycle evehicle custom1 custom2" speed="39.44" length="98.32" acceleration="1" shape="6732.78,7712.88 6700.82,7680.35 6667.51,7640.76 6666.66,7639.64">
            <param key="origId" value="95841103"/>
        </lane>
        <lane id="95841103#1-AddedOnRampEdge_1" index="1" allow="private emergency authority army vip passenger hov taxi bus coach delivery truck trailer motorcycle evehicle custom1 custom2" speed="39.44" length="98.32" shape="6735.06,7710.64 6703.19,7678.20 6669.96,7638.70 6669.22,7637.72">
            <param key="origId" value="95841103"/>
        </lane>
        <lane id="95841103#1-AddedOnRampEdge_2" index="2" allow="private emergency authority army vip passenger hov taxi bus coach delivery truck trailer motorcycle evehicle custom1 custom2" speed="39.44" length="98.32" shape="6737.34,7708.40 6705.56,7676.05 6672.41,7636.64 6671.78,7635.80">
            <param key="origId" value="95841103"/>
        </lane>
        <param key="ref" value="A 44"/>
    </edge>
    <edge id="95841114" from="1110673725" to="1110673649" name="Nó da Barrosa" priority="9" type="highway.motorway_link" spreadType="center" shape="7156.36,7884.75 7050.73,7870.75 7010.71,7868.54 6982.26,7873.07 6965.63,7879.34 6940.41,7896.24 6920.15,7920.16 6896.39,7976.72">
        <lane id="95841114_0" index="0" allow="private emergency authority army vip passenger hov taxi bus coach delivery truck trailer motorcycle evehicle custom1 custom2" speed="22.22" length="313.25" shape="7154.65,7884.52 7050.73,7870.75 7010.71,7868.54 6982.26,7873.07 6965.63,7879.34 6940.41,7896.24 6920.15,7920.16 6896.89,7975.53">
            <param key="origId" value="95841114"/>
        </lane>
    </edge>
    <edge id="95841115#0" from="685276291" to="1110673581" priority="9" type="highway.motorway_link" spreadType="center" shape="7195.89,7970.30 7203.06,7964.87 7213.89,7959.03 7220.57,7953.60 7227.42,7942.59 7230.49,7919.39 7228.61,7908.38 7224.37,7898.78 7216.88,7892.23 7204.83,7887.19">
        <lane id="95841115#0_0" index="0" allow="private emergency authority army vip passenger hov taxi bus coach delivery truck trailer motorcycle evehicle custom1 custom2" speed="22.22" length="89.52" shape="7201.97,7965.70 7203.06,7964.87 7213.89,7959.03 7220.57,7953.60 7227.42,7942.59 7230.49,7919.39 7228.61,7908.38 7224.37,7898.78 7217.44,7892.72">
            <param key="origId" value="95841115"/>
        </lane>
    </edge>
    <edge id="95841115#1" from="1110673581" to="1110673725" priority="9" type="highway.motorway_link" spreadType="center" shape="7204.64,7888.78 7156.55,7883.16">
        <lane id="95841115#1_0" index="0" allow="private emergency authority army vip passenger hov taxi bus coach delivery truck trailer motorcycle evehicle custom1 custom2" speed="22.22" length="46.79" shape="7204.45,7890.37 7157.98,7884.94">
            <param key="origId" value="95841115"/>
        </lane>
        <lane id="95841115#1_1" index="1" allow="private emergency authority army vip passenger hov taxi bus coach delivery truck trailer motorcycle evehicle custom1 custom2" speed="22.22" length="46.79" shape="7204.83,7887.19 7158.35,7881.76">
            <param key="origId" value="95841115"/>
        </lane>
    </edge>
    <edge id="95841152" from="1110673494" to="1110673581" priority="9" type="highway.motorway_link" spreadType="center">
        <lane id="95841152_0" index="0" allow="private emergency authority army vip passenger hov taxi bus coach delivery truck trailer motorcycle evehicle custom1 custom2" speed="22.22" length="43.57" shape="7261.67,7895.07 7218.51,7889.09">
            <param key="origId" value="95841152"/>
        </lane>
    </edge>
    <edge id="98835887" from="685276291" to="1143316916" name="Rua António Sampaio (Pintor)" priority="10" type="highway.tertiary" shape="7195.89,7970.30 7164.12,7982.39 7090.41,8002.21">
        <lane id="98835887_0" index="0" disallow="tram rail_urban rail rail_electric rail_fast ship" speed="22.22" length="114.22" shape="7199.96,7970.46 7164.61,7983.91 7090.83,8003.76">
            <param key="origId" value="98835887"/>
        </lane>
    </edge>
    <edge id="99185264" from="685192542" to="3389563091" name="Nó da Barrosa" priority="9" type="highway.motorway_link" spreadType="center" shape="6913.52,7708.14 6930.75,7710.74 6941.53,7714.52 6949.82,7716.44 6961.85,7717.12 6965.68,7717.01">
        <lane id="99185264_0" index="0" allow="private emergency authority army vip passenger hov taxi bus coach delivery truck trailer motorcycle evehicle custom1 custom2" speed="22.22" length="48.65" shape="6911.02,7706.14 6931.14,7709.18 6941.98,7712.98 6950.05,7714.85 6958.27,7715.32">
            <param key="origId" value="99185264"/>
        </lane>
        <lane id="99185264_1" index="1" allow="private emergency authority army vip passenger hov taxi bus coach delivery truck trailer motorcycle evehicle custom1 custom2" speed="22.22" length="48.65" shape="6910.54,7709.31 6930.36,7712.30 6941.08,7716.06 6949.59,7718.03 6958.37,7718.53">
            <param key="origId" value="99185264"/>
        </lane>
    </edge>

    <junction id="1103406302" type="dead_end" x="7435.35" y="7902.12" incLanes="474423808#1_0 474423808#1_1" intLanes="" shape="7435.80,7898.95 7434.90,7905.29"/>
    <junction id="1103406460" type="dead_end" x="7433.34" y="7911.72" incLanes="" intLanes="" shape="7433.71,7908.54 7432.60,7918.08"/>
    <junction id="1110673494" type="priority" x="7263.58" y="7895.33" incLanes="54379553-AddedOffRampEdge_0 54379553-AddedOffRampEdge_1" intLanes=":1110673494_0_0 :1110673494_1_0" shape="7264.20,7900.23 7264.90,7893.86 7262.17,7893.52 7260.30,7899.25 7261.72,7899.73 7262.22,7899.89 7262.73,7900.01 7263.35,7900.12">
        <request index="0" response="00" foes="00" cont="0"/>
        <request index="1" response="00" foes="00" cont="0"/>
    </junction>
    <junction id="1110673581" type="priority" x="7204.83" y="7887.19" incLanes="95841115#0_0 95841152_0" intLanes=":1110673581_0_0 :1110673581_1_0" shape="7216.78,7894.27 7218.11,7891.18 7218.29,7890.67 7218.73,7887.50 7205.01,7885.60 7204.27,7891.96 7207.06,7892.10 7209.26,7891.96 7211.10,7891.82 7212.81,7891.97 7214.63,7892.70">
        <request index="0" response="00" foes="00" cont="0"/>
        <request index="1" response="00" foes="00" cont="0"/>
    </junction>
    <junction id="1110673649" type="priority" x="6891.84" y="7975.19" incLanes="95841114_0 95365325_0 95365325_1" intLanes=":1110673649_0_0 :1110673649_1_0 :1110673649_1_1" shape="6898.38,7976.10 6889.39,7972.64 6888.35,7975.54 6897.45,7978.59">
        <request index="0" response="000" foes="000" cont="0"/>
        <request index="1" response="000" foes="000" cont="0"/>
        <request index="2" response="000" foes="000" cont="0"/>
    </junction>
    <junction id="1110673725" type="priority" x="7156.74" y="7881.58" incLanes="95841115#1_0 95841115#1_1" intLanes=":1110673725_0_0 :1110673725_1_0" shape="7157.79,7886.53 7158.53,7880.17 7157.43,7880.03 7157.05,7879.96 7156.67,7879.86 7156.22,7879.73 7155.62,7879.53 7154.62,7882.57 7154.86,7882.94 7154.44,7886.11">
        <request index="0" response="00" foes="00" cont="0"/>
        <request index="1" response="00" foes="00" cont="0"/>
    </junction>
    <junction id="1131360770" type="dead_end" x="7012.21" y="7642.95" incLanes="505635971_0 505635971_1 331868361#1_0" intLanes="" shape="7009.18,7641.93 7015.24,7643.97 7006.06,7641.24 7009.15,7642.10"/>
    <junction id="1143316916" type="dead_end" x="7090.41" y="8002.21" incLanes="98835887_0" intLanes="" shape="7090.41,8002.21 7091.24,8005.30 7090.41,8002.21"/>
    <junction id="1147305736" type="dead_end" x="6631.41" y="7547.87" incLanes="" intLanes="" shape="6628.67,7549.52 6636.89,7544.56"/>
    <junction id="269354454" type="priority" x="6740.31" y="7695.75" incLanes="474423810_0 474423810_1 474423810_2" intLanes=":269354454_0_0 :269354454_1_0 :269354454_1_1" shape="6739.12,7699.19 6743.85,7694.87 6744.25,7694.86 6746.21,7692.33 6745.34,7691.65 6745.04,7691.39 6744.77,7691.11 6744.45,7690.77 6744.03,7690.29 6736.84,7696.66">
        <request index="0" response="000" foes="000" cont="0"/>
        <request index="1" response="000" foes="000" cont="0"/>
        <request index="2" response="000" foes="000" cont="0"/>
    </junction>
    <junction id="269354459" type="priority" x="7043.88" y="7846.07" incLanes="474423809_0 474423809_1 474423809_2" intLanes=":269354459_0_0 :269354459_0_1" shape="7047.19,7849.82 7048.18,7843.50 7045.53,7842.66 7044.68,7842.11 7043.84,7841.54 7042.76,7841.00 7041.23,7840.51 7039.03,7849.86 7042.02,7850.13 7043.09,7849.96 7044.17,7849.76 7045.46,7849.67">
        <request index="0" response="00" foes="00" cont="0"/>
        <request index="1" response="00" foes="00" cont="0"/>
    </junction>
    <junction id="269355962" type="dead_end" x="6619.60" y="7559.02" incLanes="95841103#1_0 95841103#1_1 95841103#1_2" intLanes="" shape="6614.02,7562.15 6622.40,7557.45"/>
    <junction id="331868361#0-AddedOffRampNode" type="priority" x="6814.92" y="7723.78" incLanes="331868361#0_0" intLanes=":331868361#0-AddedOffRampNode_0_0 :331868361#0-AddedOffRampNode_0_1 :331868361#0-AddedOffRampNode_0_2" shape="6818.77,7725.59 6819.56,7715.86 6817.49,7716.51 6816.21,7717.74 6815.31,7719.21 6814.42,7720.61 6813.13,7721.60 6811.06,7721.85 6810.80,7725.04 6813.75,7725.42 6814.79,7725.59 6815.82,7725.70 6817.08,7725.71">
        <request index="0" response="000" foes="000" cont="0"/>
        <request index="1" response="000" foes="000" cont="0"/>
        <request index="2" response="000" foes="000" cont="0"/>
    </junction>
    <junction id="332557431-AddedOnRampNode" type="dead_end" x="6855.17" y="8068.10" incLanes="332557431-AddedOnRampEdge_0 332557431-AddedOnRampEdge_1 332557431-AddedOnRampEdge_2" intLanes="" shape="6861.03,8070.71 6852.26,8066.80"/>
    <junction id="3389563082" type="priority" x="6981.55" y="7707.88" incLanes="331866644#3_0 331866644#3_1" intLanes=":3389563082_0_0 :3389563082_0_1 :3389563082_2_0 :3389563082_2_1" shape="6991.35,7711.32 6991.33,7704.56 6990.81,7704.29 6990.69,7704.13 6990.67,7703.96 6990.75,7703.77 6990.93,7703.56 6986.47,7698.77 6985.23,7700.69 6984.22,7702.12 6983.24,7703.18 6982.09,7704.02 6980.55,7704.78 6978.44,7705.62 6980.65,7711.62 6982.83,7710.84 6984.53,7710.34 6985.98,7710.14 6987.44,7710.23 6989.14,7710.62">
        <request index="0" response="0000" foes="0000" cont="0"/>
        <request index="1" response="0000" foes="0000" cont="0"/>
        <request index="2" response="0000" foes="0000" cont="0"/>
        <request index="3" response="0000" foes="0000" cont="0"/>
    </junction>
    <junction id="3389563087" type="priority" x="6993.12" y="7761.28" incLanes="331866644#6_0 331866644#6_1" intLanes=":3389563087_0_0 :3389563087_0_1 :3389563087_2_0 :3389563087_2_1" shape="6996.16,7763.49 6993.73,7757.57 6990.77,7758.64 6988.49,7759.12 6986.52,7759.14 6984.52,7758.81 6982.13,7758.26 6979.00,7757.59 6979.60,7764.22 6980.28,7764.46 6980.38,7764.61 6980.34,7764.80 6980.13,7765.01 6979.78,7765.24 6982.96,7770.79 6985.73,7769.15 6987.74,7767.87 6989.40,7766.81 6991.09,7765.82 6993.21,7764.77">
        <request index="0" response="0000" foes="0000" cont="0"/>
        <request index="1" response="0000" foes="0000" cont="0"/>
        <request index="2" response="0000" foes="0000" cont="0"/>
        <request index="3" response="0000" foes="0000" cont="0"/>
    </junction>
    <junction id="3389563088" type="priority" x="7006.92" y="7716.47" incLanes="331866644#4_0 331866644#4_1" intLanes=":3389563088_0_0 :3389563088_0_1" shape="7004.54,7718.67 7009.87,7715.12 7009.44,7714.50 7009.27,7714.30 7009.08,7714.11 7008.83,7713.91 7008.50,7713.64">
        <request index="0" response="00" foes="00" cont="0"/>
        <request index="1" response="00" foes="00" cont="0"/>
    </junction>
    <junction id="3389563089" type="priority" x="7011.34" y="7746.42" incLanes="331866644#5_0 331866644#5_1" intLanes=":3389563089_0_0 :3389563089_0_1" shape="7014.54,7746.90 7008.42,7745.03 7013.73,7748.60 7014.11,7748.01 7014.23,7747.79 7014.33,7747.56 7014.42,7747.28">
        <request index="0" response="00" foes="00" cont="0"/>
        <request index="1" response="00" foes="00" cont="0"/>
    </junction>
    <junction id="3389563091" type="priority" x="6965.68" y="7717.01" incLanes="99185264_0 99185264_1 331866644#2_0 331866644#2_1" intLanes=":3389563091_0_0 :3389563091_0_1 :3389563091_2_0 :3389563091_2_1" shape="6969.72,7717.82 6965.64,7712.89 6963.27,7714.20 6962.25,7714.27 6961.17,7714.12 6959.87,7713.89 6958.23,7713.71 6958.41,7720.13 6959.16,7720.32 6959.34,7720.51 6959.39,7720.77 6959.32,7721.10 6959.12,7721.49 6964.55,7724.88 6966.17,7722.01 6966.74,7721.00 6967.40,7720.06 6968.33,7719.05">
        <request index="0" response="0100" foes="0100" cont="0"/>
        <request index="1" response="1100" foes="1100" cont="0"/>
        <request index="2" response="0000" foes="0011" cont="0"/>
        <request index="3" response="0000" foes="0010" cont="0"/>
    </junction>
    <junction id="3970730290" type="priority" x="6962.52" y="7747.93" incLanes="331866644#1_0 331866644#1_1" intLanes=":3970730290_0_0 :3970730290_1_0 :3970730290_1_1" shape="6962.27,7753.34 6967.60,7749.80 6963.91,7726.74 6956.73,7728.93 6955.94,7730.65 6955.41,7731.00 6954.79,7731.00 6954.09,7730.66 6953.30,7729.97 6950.36,7731.54">
        <request index="0" response="000" foes="000" cont="0"/>
        <request index="1" response="000" foes="000" cont="0"/>
        <request index="2" response="000" foes="000" cont="0"/>
    </junction>
    <junction id="474423808#1-AddedOnRampNode" type="priority" x="7201.45" y="7868.67" incLanes="474423808#1-AddedOnRampEdge_0 474423808#1-AddedOnRampEdge_1 474423808#1-AddedOnRampEdge_2" intLanes=":474423808#1-AddedOnRampNode_0_0 :474423808#1-AddedOnRampNode_0_1" shape="7204.98,7872.38 7205.85,7866.04 7202.96,7864.81 7201.24,7863.02 7200.09,7862.26 7198.35,7861.78 7197.06,7871.30">
        <request index="0" response="00" foes="00" cont="0"/>
        <request index="1" response="00" foes="00" cont="0"/>
    </junction>
    <junction id="4955227553" type="priority" x="6909.78" y="7806.98" incLanes="95362523_0 95362523_1" intLanes=":4955227553_0_0 :4955227553_0_1 :4955227553_0_2" shape="6911.43,7812.98 6915.35,7804.21 6912.44,7803.37 6911.34,7803.32 6910.24,7803.28 6908.95,7803.08 6907.28,7802.55 6904.93,7808.50 6907.44,7809.95 6908.20,7810.68 6908.96,7811.42 6909.95,7812.19">
        <request index="0" response="000" foes="000" cont="0"/>
        <request index="1" response="000" foes="000" cont="0"/>
        <request index="2" response="000" foes="000" cont="0"/>
    </junction>
    <junction id="4955227555" type="priority" x="7102.37" y="7855.17" incLanes="474423808#0_0 474423808#0_1 394028171_0" intLanes=":4955227555_0_0 :4955227555_0_1 :4955227555_2_0" shape="7103.43,7858.55 7104.72,7849.04 7101.68,7848.64 7100.21,7858.07">
        <request index="0" response="000" foes="000" cont="0"/>
        <request index="1" response="000" foes="000" cont="0"/>
        <request index="2" response="000" foes="000" cont="0"/>
    </junction>
    <junction id="54379553-AddedOffRampNode" type="priority" x="7363.10" y="7904.69" incLanes="54379553_0" intLanes=":54379553-AddedOffRampNode_0_0 :54379553-AddedOffRampNode_0_1" shape="7375.84,7911.23 7376.97,7908.23 7374.07,7906.96 7371.96,7905.80 7370.24,7904.78 7368.48,7903.96 7366.26,7903.38 7363.15,7903.09 7362.93,7909.49 7365.72,7909.54 7367.82,7909.53 7369.54,7909.58 7371.23,7909.80 7373.22,7910.31">
        <request index="0" response="00" foes="00" cont="0"/>
        <request index="1" response="00" foes="00" cont="0"/>
    </junction>
    <junction id="546895481-AddedOffRampNode" type="dead_end" x="6822.71" y="8100.91" incLanes="" intLanes="" shape="6825.51,8102.46 6817.11,8097.82"/>
    <junction id="685192542" type="priority" x="6913.52" y="7708.14" incLanes="331868361#0-AddedOffRampEdge_0 331868361#0-AddedOffRampEdge_1 331868361#0-AddedOffRampEdge_2" intLanes=":685192542_0_0 :685192542_1_0 :685192542_1_1" shape="6910.30,7710.89 6911.25,7704.56 6913.97,7703.30 6913.67,7700.12 6910.64,7700.48 6909.59,7700.67 6908.54,7700.90 6907.27,7701.17 6905.55,7701.51 6907.34,7710.95 6908.43,7710.76 6908.82,7710.73 6909.21,7710.75 6909.67,7710.80">
        <request index="0" response="000" foes="000" cont="0"/>
        <request index="1" response="000" foes="000" cont="0"/>
        <request index="2" response="000" foes="000" cont="0"/>
    </junction>
    <junction id="685192553" type="priority" x="6964.99" y="7751.65" incLanes="331866644#7_0 331866644#7_1 95365322_0 95365322_1" intLanes=":685192553_0_0 :685192553_0_1 :685192553_2_0 :685192553_2_1" shape="6968.63,7759.52 6973.16,7754.71 6971.30,7753.70 6970.00,7752.81 6969.05,7751.90 6968.24,7750.84 6967.36,7749.48 6966.20,7747.68 6960.87,7751.22 6962.00,7753.94 6961.94,7755.05 6961.66,7756.21 6961.31,7757.59 6961.03,7759.37 6967.40,7759.98 6967.60,7759.26 6967.78,7759.12 6968.01,7759.11 6968.30,7759.25">
        <request index="0" response="0000" foes="1100" cont="0"/>
        <request index="1" response="0000" foes="1000" cont="0"/>
        <request index="2" response="0001" foes="0001" cont="0"/>
        <request index="3" response="0011" foes="0011" cont="0"/>
    </junction>
    <junction id="685192577" type="priority" x="6867.53" y="8011.57" incLanes="546895481-AddedOffRampEdge_0 546895481-AddedOffRampEdge_1 546895481-AddedOffRampEdge_2" intLanes=":685192577_0_0 :685192577_1_0 :685192577_1_1" shape="6871.23,8010.95 6865.30,8008.55 6865.18,8008.38 6862.10,8007.50 6861.79,8008.57 6861.66,8008.94 6861.52,8009.30 6861.32,8009.73 6861.05,8010.30 6869.71,8014.44">
        <request index="0" response="000" foes="000" cont="0"/>
        <request index="1" response="000" foes="000" cont="0"/>
        <request index="2" response="000" foes="000" cont="0"/>
    </junction>
    <junction id="685276223" type="priority" x="6737.41" y="7710.75" incLanes="95117787#2_0 95117787#2_1 54379491_0" intLanes=":685276223_0_0 :685276223_0_1 :685276223_2_0" shape="6735.25,7716.48 6740.73,7709.25 6739.85,7708.57 6739.55,7708.32 6739.27,7708.06 6738.93,7707.73 6738.48,7707.27 6731.64,7714.00 6732.81,7715.13 6733.27,7715.48 6733.77,7715.77 6734.40,7716.08">
        <request index="0" response="000" foes="000" cont="0"/>
        <request index="1" response="000" foes="000" cont="0"/>
        <request index="2" response="000" foes="000" cont="0"/>
    </junction>
    <junction id="685276291" type="priority" x="7195.89" y="7970.30" incLanes="1010075428_0 -98835887_0" intLanes=":685276291_0_0 :685276291_4_0 :685276291_2_0 :685276291_5_0" shape="7204.82,7970.69 7204.39,7967.52 7203.05,7967.62 7202.70,7967.56 7202.56,7967.44 7202.64,7967.24 7202.93,7966.97 7201.00,7964.42 7200.05,7965.13 7199.71,7965.35 7199.34,7965.54 7198.88,7965.73 7198.25,7965.98 7200.52,7971.96 7202.08,7971.34 7202.63,7971.14 7203.19,7970.97 7203.88,7970.83">
        <request index="0" response="0000" foes="1000" cont="0"/>
        <request index="1" response="0100" foes="0100" cont="1"/>
        <request index="2" response="0000" foes="0010" cont="0"/>
        <request index="3" response="0001" foes="0001" cont="1"/>
    </junction>
    <junction id="685276345" type="priority" x="7377.60" y="7905.21" incLanes="95117787#0_0 95117787#0_1 95117787#0_2" intLanes=":685276345_0_0 :685276345_1_0 :685276345_1_1" shape="7377.98,7911.69 7379.09,7902.15 7376.53,7901.81 7373.25,7910.25 7374.96,7910.95 7375.56,7911.19 7376.18,7911.38 7376.94,7911.54">
        <request index="0" response="000" foes="000" cont="0"/>
        <request index="1" response="000" foes="000" cont="0"/>
        <request index="2" response="000" foes="000" cont="0"/>
    </junction>
    <junction id="685276959" type="priority" x="7045.74" y="7857.61" incLanes="1067636645_0 95117787#1_0 95117787#1_1" intLanes=":685276959_0_0 :685276959_1_0 :685276959_1_1" shape="7046.19,7864.14 7047.31,7854.57 7046.52,7854.47 7046.24,7854.43 7045.97,7854.38 7045.64,7854.31 7045.19,7854.21 7043.16,7863.60">
        <request index="0" response="000" foes="000" cont="0"/>
        <request index="1" response="000" foes="000" cont="0"/>
        <request index="2" response="000" foes="000" cont="0"/>
    </junction>
    <junction id="95117787#2-AddedOnRampNode" type="priority" x="6949.10" y="7832.21" incLanes="95117787#2-AddedOnRampEdge_0 95117787#2-AddedOnRampEdge_1 95117787#2-AddedOnRampEdge_2" intLanes=":95117787#2-AddedOnRampNode_0_0 :95117787#2-AddedOnRampNode_0_1" shape="6950.94,7839.53 6953.88,7830.39 6946.27,7827.94 6944.31,7834.03 6946.94,7835.75 6948.31,7837.81 6949.31,7838.75">
        <request index="0" response="00" foes="00" cont="0"/>
        <request index="1" response="00" foes="00" cont="0"/>
    </junction>
    <junction id="95841103#1-AddedOnRampNode" type="priority" x="6670.41" y="7636.63" incLanes="95841103#1-AddedOnRampEdge_0 95841103#1-AddedOnRampEdge_1 95841103#1-AddedOnRampEdge_2" intLanes=":95841103#1-AddedOnRampNode_0_0 :95841103#1-AddedOnRampNode_0_1 :95841103#1-AddedOnRampNode_0_2" shape="6665.38,7640.60 6673.06,7634.84 6672.88,7634.59 6665.19,7640.33">
        <request index="0" response="000" foes="000" cont="0"/>
        <request index="1" response="000" foes="000" cont="0"/>
        <request index="2" response="000" foes="000" cont="0"/>
    </junction>

    <junction id=":685276291_4_0" type="internal" x="7200.98" y="7969.28" incLanes=":685276291_1_0 -98835887_0" intLanes=":685276291_2_0"/>
    <junction id=":685276291_5_0" type="internal" x="7200.22" y="7967.79" incLanes=":685276291_3_0 1010075428_0" intLanes=":685276291_0_0"/>

    <connection from="-98835887" to="95841115#0" fromLane="0" toLane="0" via=":685276291_2_0" dir="s" state="M"/>
    <connection from="-98835887" to="98835887" fromLane="0" toLane="0" via=":685276291_3_0" dir="t" state="m"/>
    <connection from="1010075428" to="98835887" fromLane="0" toLane="0" via=":685276291_0_0" dir="s" state="M"/>
    <connection from="1010075428" to="95841115#0" fromLane="0" toLane="0" via=":685276291_1_0" dir="l" state="m"/>
    <connection from="1067636645" to="95117787#2-AddedOnRampEdge" fromLane="0" toLane="0" via=":685276959_0_0" dir="s" state="M"/>
    <connection from="331866644#1" to="394028171" fromLane="0" toLane="0" via=":3970730290_0_0" dir="s" state="M"/>
    <connection from="331866644#1" to="331866644#2" fromLane="0" toLane="0" via=":3970730290_1_0" dir="s" state="M"/>
    <connection from="331866644#1" to="331866644#2" fromLane="1" toLane="1" via=":3970730290_1_1" dir="s" state="M"/>
    <connection from="331866644#2" to="331866644#3" fromLane="0" toLane="0" via=":3389563091_2_0" dir="s" state="M"/>
    <connection from="331866644#2" to="331866644#3" fromLane="1" toLane="1" via=":3389563091_2_1" dir="s" state="M"/>
    <connection from="331866644#3" to="505635971" fromLane="0" toLane="0" via=":3389563082_0_0" dir="R" state="M"/>
    <connection from="331866644#3" to="505635971" fromLane="0" toLane="1" via=":3389563082_0_1" dir="R" state="M"/>
    <connection from="331866644#3" to="331866644#4" fromLane="0" toLane="0" via=":3389563082_2_0" dir="s" state="M"/>
    <connection from="331866644#3" to="331866644#4" fromLane="1" toLane="1" via=":3389563082_2_1" dir="s" state="M"/>
    <connection from="331866644#4" to="331866644#5" fromLane="0" toLane="0" via=":3389563088_0_0" dir="s" state="M"/>
    <connection from="331866644#4" to="331866644#5" fromLane="1" toLane="1" via=":3389563088_0_1" dir="s" state="M"/>
    <connection from="331866644#5" to="331866644#6" fromLane="0" toLane="0" via=":3389563089_0_0" dir="s" state="M"/>
    <connection from="331866644#5" to="331866644#6" fromLane="1" toLane="1" via=":3389563089_0_1" dir="s" state="M"/>
    <connection from="331866644#6" to="95365325" fromLane="0" toLane="0" via=":3389563087_0_0" dir="R" state="M"/>
    <connection from="331866644#6" to="95365325" fromLane="0" toLane="1" via=":3389563087_0_1" dir="R" state="M"/>
    <connection from="331866644#6" to="331866644#7" fromLane="0" toLane="0" via=":3389563087_2_0" dir="s" state="M"/>
    <connection from="331866644#6" to="331866644#7" fromLane="1" toLane="1" via=":3389563087_2_1" dir="s" state="M"/>
    <connection from="331866644#7" to="331866644#1" fromLane="0" toLane="0" via=":685192553_0_0" dir="s" state="M"/>
    <connection from="331866644#7" to="331866644#1" fromLane="1" toLane="1" via=":685192553_0_1" dir="s" state="M"/>
    <connection from="331868361#0" to="331868361#0-AddedOffRampEdge" fromLane="0" toLane="0" via=":331868361#0-AddedOffRampNode_0_0" dir="s" state="M"/>
    <connection from="331868361#0" to="331868361#0-AddedOffRampEdge" fromLane="0" toLane="1" via=":331868361#0-AddedOffRampNode_0_1" dir="s" state="M"/>
    <connection from="331868361#0" to="331868361#0-AddedOffRampEdge" fromLane="0" toLane="2" via=":331868361#0-AddedOffRampNode_0_2" dir="s" state="M"/>
    <connection from="331868361#0-AddedOffRampEdge" to="331868361#1" fromLane="0" toLane="0" via=":685192542_0_0" dir="s" state="M"/>
    <connection from="331868361#0-AddedOffRampEdge" to="99185264" fromLane="1" toLane="0" via=":685192542_1_0" dir="L" state="M"/>
    <connection from="331868361#0-AddedOffRampEdge" to="99185264" fromLane="2" toLane="1" via=":685192542_1_1" dir="L" state="M"/>
    <connection from="394028171" to="474423808#1-AddedOnRampEdge" fromLane="0" toLane="0" via=":4955227555_2_0" dir="s" state="M"/>
    <connection from="474423808#0" to="474423808#1-AddedOnRampEdge" fromLane="0" toLane="1" via=":4955227555_0_0" dir="s" state="M"/>
    <connection from="474423808#0" to="474423808#1-AddedOnRampEdge" fromLane="1" toLane="2" via=":4955227555_0_1" dir="s" state="M"/>
    <connection from="474423808#1-AddedOnRampEdge" to="474423808#1" fromLane="1" toLane="0" via=":474423808#1-AddedOnRampNode_0_0" dir="s" state="M"/>
    <connection from="474423808#1-AddedOnRampEdge" to="474423808#1" fromLane="2" toLane="1" via=":474423808#1-AddedOnRampNode_0_1" dir="s" state="M"/>
    <connection from="474423809" to="474423808#0" fromLane="1" toLane="0" via=":269354459_0_0" dir="s" state="M"/>
    <connection from="474423809" to="474423808#0" fromLane="2" toLane="1" via=":269354459_0_1" dir="s" state="M"/>
    <connection from="474423810" to="331868361#0" fromLane="0" toLane="0" via=":269354454_0_0" dir="R" state="M"/>
    <connection from="474423810" to="95362523" fromLane="1" toLane="0" via=":269354454_1_0" dir="s" state="M"/>
    <connection from="474423810" to="95362523" fromLane="2" toLane="1" via=":269354454_1_1" dir="s" state="M"/>
    <connection from="54379491" to="95841103#1-AddedOnRampEdge" fromLane="0" toLane="0" via=":685276223_2_0" dir="s" state="M"/>
    <connection from="54379553" to="54379553-AddedOffRampEdge" fromLane="0" toLane="0" via=":54379553-AddedOffRampNode_0_0" dir="s" state="M"/>
    <connection from="54379553" to="54379553-AddedOffRampEdge" fromLane="0" toLane="1" via=":54379553-AddedOffRampNode_0_1" dir="s" state="M"/>
    <connection from="54379553-AddedOffRampEdge" to="1010075428" fromLane="0" toLane="0" via=":1110673494_0_0" dir="L" state="M"/>
    <connection from="54379553-AddedOffRampEdge" to="95841152" fromLane="1" toLane="0" via=":1110673494_1_0" dir="s" state="M"/>
    <connection from="546895481-AddedOffRampEdge" to="54379491" fromLane="0" toLane="0" via=":685192577_0_0" dir="R" state="M"/>
    <connection from="546895481-AddedOffRampEdge" to="95365322" fromLane="1" toLane="0" via=":685192577_1_0" dir="s" state="M"/>
    <connection from="546895481-AddedOffRampEdge" to="95365322" fromLane="2" toLane="1" via=":685192577_1_1" dir="s" state="M"/>
    <connection from="95117787#0" to="54379553" fromLane="0" toLane="0" via=":685276345_0_0" dir="L" state="M"/>
    <connection from="95117787#0" to="95117787#1" fromLane="1" toLane="0" via=":685276345_1_0" dir="s" state="M"/>
    <connection from="95117787#0" to="95117787#1" fromLane="2" toLane="1" via=":685276345_1_1" dir="s" state="M"/>
    <connection from="95117787#1" to="95117787#2-AddedOnRampEdge" fromLane="0" toLane="1" via=":685276959_1_0" dir="s" state="M"/>
    <connection from="95117787#1" to="95117787#2-AddedOnRampEdge" fromLane="1" toLane="2" via=":685276959_1_1" dir="s" state="M"/>
    <connection from="95117787#2" to="95841103#1-AddedOnRampEdge" fromLane="0" toLane="1" via=":685276223_0_0" dir="s" state="M"/>
    <connection from="95117787#2" to="95841103#1-AddedOnRampEdge" fromLane="1" toLane="2" via=":685276223_0_1" dir="s" state="M"/>
    <connection from="95117787#2-AddedOnRampEdge" to="95117787#2" fromLane="1" toLane="0" via=":95117787#2-AddedOnRampNode_0_0" dir="s" state="M"/>
    <connection from="95117787#2-AddedOnRampEdge" to="95117787#2" fromLane="2" toLane="1" via=":95117787#2-AddedOnRampNode_0_1" dir="s" state="M"/>
    <connection from="95362523" to="474423809" fromLane="0" toLane="0" via=":4955227553_0_0" dir="s" state="M"/>
    <connection from="95362523" to="474423809" fromLane="0" toLane="1" via=":4955227553_0_1" dir="s" state="M"/>
    <connection from="95362523" to="474423809" fromLane="1" toLane="2" via=":4955227553_0_2" dir="s" state="M"/>
    <connection from="95365322" to="331866644#1" fromLane="0" toLane="0" via=":685192553_2_0" dir="s" state="m" visibility="9.00"/>
    <connection from="95365322" to="331866644#1" fromLane="1" toLane="1" via=":685192553_2_1" dir="s" state="m" visibility="9.00"/>
    <connection from="95365325" to="332557431-AddedOnRampEdge" fromLane="0" toLane="1" via=":1110673649_1_0" dir="s" state="M"/>
    <connection from="95365325" to="332557431-AddedOnRampEdge" fromLane="1" toLane="2" via=":1110673649_1_1" dir="s" state="M"/>
    <connection from="95841103#1-AddedOnRampEdge" to="95841103#1" fromLane="0" toLane="0" via=":95841103#1-AddedOnRampNode_0_0" dir="s" state="M"/>
    <connection from="95841103#1-AddedOnRampEdge" to="95841103#1" fromLane="1" toLane="1" via=":95841103#1-AddedOnRampNode_0_1" dir="s" state="M"/>
    <connection from="95841103#1-AddedOnRampEdge" to="95841103#1" fromLane="2" toLane="2" via=":95841103#1-AddedOnRampNode_0_2" dir="s" state="M"/>
    <connection from="95841114" to="332557431-AddedOnRampEdge" fromLane="0" toLane="0" via=":1110673649_0_0" dir="s" state="M"/>
    <connection from="95841115#0" to="95841115#1" fromLane="0" toLane="0" via=":1110673581_0_0" dir="s" state="M"/>
    <connection from="95841115#1" to="95841114" fromLane="0" toLane="0" via=":1110673725_0_0" dir="s" state="M"/>
    <connection from="95841115#1" to="1067636645" fromLane="1" toLane="0" via=":1110673725_1_0" dir="L" state="M"/>
    <connection from="95841152" to="95841115#1" fromLane="0" toLane="1" via=":1110673581_1_0" dir="s" state="M"/>
    <connection from="99185264" to="331866644#3" fromLane="0" toLane="0" via=":3389563091_0_0" dir="s" state="m" visibility="9.00"/>
    <connection from="99185264" to="331866644#3" fromLane="1" toLane="1" via=":3389563091_0_1" dir="s" state="m" visibility="9.00"/>

    <connection from=":1110673494_0" to="1010075428" fromLane="0" toLane="0" dir="L" state="M"/>
    <connection from=":1110673494_1" to="95841152" fromLane="0" toLane="0" dir="s" state="M"/>
    <connection from=":1110673581_0" to="95841115#1" fromLane="0" toLane="0" dir="s" state="M"/>
    <connection from=":1110673581_1" to="95841115#1" fromLane="0" toLane="1" dir="s" state="M"/>
    <connection from=":1110673649_0" to="332557431-AddedOnRampEdge" fromLane="0" toLane="0" dir="s" state="M"/>
    <connection from=":1110673649_1" to="332557431-AddedOnRampEdge" fromLane="0" toLane="1" dir="s" state="M"/>
    <connection from=":1110673649_1" to="332557431-AddedOnRampEdge" fromLane="1" toLane="2" dir="s" state="M"/>
    <connection from=":1110673725_0" to="95841114" fromLane="0" toLane="0" dir="s" state="M"/>
    <connection from=":1110673725_1" to="1067636645" fromLane="0" toLane="0" dir="L" state="M"/>
    <connection from=":269354454_0" to="331868361#0" fromLane="0" toLane="0" dir="R" state="M"/>
    <connection from=":269354454_1" to="95362523" fromLane="0" toLane="0" dir="s" state="M"/>
    <connection from=":269354454_1" to="95362523" fromLane="1" toLane="1" dir="s" state="M"/>
    <connection from=":269354459_0" to="474423808#0" fromLane="0" toLane="0" dir="s" state="M"/>
    <connection from=":269354459_0" to="474423808#0" fromLane="1" toLane="1" dir="s" state="M"/>
    <connection from=":331868361#0-AddedOffRampNode_0" to="331868361#0-AddedOffRampEdge" fromLane="0" toLane="0" dir="s" state="M"/>
    <connection from=":331868361#0-AddedOffRampNode_0" to="331868361#0-AddedOffRampEdge" fromLane="1" toLane="1" dir="s" state="M"/>
    <connection from=":331868361#0-AddedOffRampNode_0" to="331868361#0-AddedOffRampEdge" fromLane="2" toLane="2" dir="s" state="M"/>
    <connection from=":3389563082_0" to="505635971" fromLane="0" toLane="0" dir="R" state="M"/>
    <connection from=":3389563082_0" to="505635971" fromLane="1" toLane="1" dir="R" state="M"/>
    <connection from=":3389563082_2" to="331866644#4" fromLane="0" toLane="0" dir="s" state="M"/>
    <connection from=":3389563082_2" to="331866644#4" fromLane="1" toLane="1" dir="s" state="M"/>
    <connection from=":3389563087_0" to="95365325" fromLane="0" toLane="0" dir="R" state="M"/>
    <connection from=":3389563087_0" to="95365325" fromLane="1" toLane="1" dir="R" state="M"/>
    <connection from=":3389563087_2" to="331866644#7" fromLane="0" toLane="0" dir="s" state="M"/>
    <connection from=":3389563087_2" to="331866644#7" fromLane="1" toLane="1" dir="s" state="M"/>
    <connection from=":3389563088_0" to="331866644#5" fromLane="0" toLane="0" dir="s" state="M"/>
    <connection from=":3389563088_0" to="331866644#5" fromLane="1" toLane="1" dir="s" state="M"/>
    <connection from=":3389563089_0" to="331866644#6" fromLane="0" toLane="0" dir="s" state="M"/>
    <connection from=":3389563089_0" to="331866644#6" fromLane="1" toLane="1" dir="s" state="M"/>
    <connection from=":3389563091_0" to="331866644#3" fromLane="0" toLane="0" dir="s" state="M"/>
    <connection from=":3389563091_0" to="331866644#3" fromLane="1" toLane="1" dir="s" state="M"/>
    <connection from=":3389563091_2" to="331866644#3" fromLane="0" toLane="0" dir="s" state="M"/>
    <connection from=":3389563091_2" to="331866644#3" fromLane="1" toLane="1" dir="s" state="M"/>
    <connection from=":3970730290_0" to="394028171" fromLane="0" toLane="0" dir="s" state="M"/>
    <connection from=":3970730290_1" to="331866644#2" fromLane="0" toLane="0" dir="s" state="M"/>
    <connection from=":3970730290_1" to="331866644#2" fromLane="1" toLane="1" dir="s" state="M"/>
    <connection from=":474423808#1-AddedOnRampNode_0" to="474423808#1" fromLane="0" toLane="0" dir="s" state="M"/>
    <connection from=":474423808#1-AddedOnRampNode_0" to="474423808#1" fromLane="1" toLane="1" dir="s" state="M"/>
    <connection from=":4955227553_0" to="474423809" fromLane="0" toLane="0" dir="s" state="M"/>
    <connection from=":4955227553_0" to="474423809" fromLane="1" toLane="1" dir="s" state="M"/>
    <connection from=":4955227553_0" to="474423809" fromLane="2" toLane="2" dir="s" state="M"/>
    <connection from=":4955227555_0" to="474423808#1-AddedOnRampEdge" fromLane="0" toLane="1" dir="s" state="M"/>
    <connection from=":4955227555_0" to="474423808#1-AddedOnRampEdge" fromLane="1" toLane="2" dir="s" state="M"/>
    <connection from=":4955227555_2" to="474423808#1-AddedOnRampEdge" fromLane="0" toLane="0" dir="s" state="M"/>
    <connection from=":54379553-AddedOffRampNode_0" to="54379553-AddedOffRampEdge" fromLane="0" toLane="0" dir="s" state="M"/>
    <connection from=":54379553-AddedOffRampNode_0" to="54379553-AddedOffRampEdge" fromLane="1" toLane="1" dir="s" state="M"/>
    <connection from=":685192542_0" to="331868361#1" fromLane="0" toLane="0" dir="s" state="M"/>
    <connection from=":685192542_1" to="99185264" fromLane="0" toLane="0" dir="L" state="M"/>
    <connection from=":685192542_1" to="99185264" fromLane="1" toLane="1" dir="L" state="M"/>
    <connection from=":685192553_0" to="331866644#1" fromLane="0" toLane="0" dir="s" state="M"/>
    <connection from=":685192553_0" to="331866644#1" fromLane="1" toLane="1" dir="s" state="M"/>
    <connection from=":685192553_2" to="331866644#1" fromLane="0" toLane="0" dir="s" state="M"/>
    <connection from=":685192553_2" to="331866644#1" fromLane="1" toLane="1" dir="s" state="M"/>
    <connection from=":685192577_0" to="54379491" fromLane="0" toLane="0" dir="R" state="M"/>
    <connection from=":685192577_1" to="95365322" fromLane="0" toLane="0" dir="s" state="M"/>
    <connection from=":685192577_1" to="95365322" fromLane="1" toLane="1" dir="s" state="M"/>
    <connection from=":685276223_0" to="95841103#1-AddedOnRampEdge" fromLane="0" toLane="1" dir="s" state="M"/>
    <connection from=":685276223_0" to="95841103#1-AddedOnRampEdge" fromLane="1" toLane="2" dir="s" state="M"/>
    <connection from=":685276223_2" to="95841103#1-AddedOnRampEdge" fromLane="0" toLane="0" dir="s" state="M"/>
    <connection from=":685276291_0" to="98835887" fromLane="0" toLane="0" dir="s" state="M"/>
    <connection from=":685276291_1" to="95841115#0" fromLane="0" toLane="0" via=":685276291_4_0" dir="l" state="m"/>
    <connection from=":685276291_4" to="95841115#0" fromLane="0" toLane="0" dir="l" state="M"/>
    <connection from=":685276291_2" to="95841115#0" fromLane="0" toLane="0" dir="s" state="M"/>
    <connection from=":685276291_3" to="98835887" fromLane="0" toLane="0" via=":685276291_5_0" dir="t" state="m"/>
    <connection from=":685276291_5" to="98835887" fromLane="0" toLane="0" dir="t" state="M"/>
    <connection from=":685276345_0" to="54379553" fromLane="0" toLane="0" dir="L" state="M"/>
    <connection from=":685276345_1" to="95117787#1" fromLane="0" toLane="0" dir="s" state="M"/>
    <connection from=":685276345_1" to="95117787#1" fromLane="1" toLane="1" dir="s" state="M"/>
    <connection from=":685276959_0" to="95117787#2-AddedOnRampEdge" fromLane="0" toLane="0" dir="s" state="M"/>
    <connection from=":685276959_1" to="95117787#2-AddedOnRampEdge" fromLane="0" toLane="1" dir="s" state="M"/>
    <connection from=":685276959_1" to="95117787#2-AddedOnRampEdge" fromLane="1" toLane="2" dir="s" state="M"/>
    <connection from=":95117787#2-AddedOnRampNode_0" to="95117787#2" fromLane="0" toLane="0" dir="s" state="M"/>
    <connection from=":95117787#2-AddedOnRampNode_0" to="95117787#2" fromLane="1" toLane="1" dir="s" state="M"/>
    <connection from=":95841103#1-AddedOnRampNode_0" to="95841103#1" fromLane="0" toLane="0" dir="s" state="M"/>
    <connection from=":95841103#1-AddedOnRampNode_0" to="95841103#1" fromLane="1" toLane="1" dir="s" state="M"/>
    <connection from=":95841103#1-AddedOnRampNode_0" to="95841103#1" fromLane="2" toLane="2" dir="s" state="M"/>

    <roundabout nodes="3389563082 3389563087 3389563088 3389563089 3389563091 3970730290 685192553" edges="331866644#1 331866644#2 331866644#3 331866644#4 331866644#5 331866644#6 331866644#7"/>

</net>
